<?xml version="1.0" encoding="utf-8"?><bwFonts xmlns:xsi="http://www.w3.org/2001/XMLSchema-instance" xmlns:xsd="http://www.w3.org/2001/XMLSchema" fontfactoryurl="story_content/FontFactory.swf"><font id="00" name="Open SansBold Charset1_ 6DpPuj84Y91"><glyphs><g i="0" c="1053" charCode="1053" p="%^SM$v5J$v5Jjo1Cjo1C$vfy$vfy9e1C9e1C9l5J9l5J9eSM9e" /><g i="1" c="1077" charCode="1077" p="#^CDLkqCLkLBvl4Bfm_ADn%cGDnaGfmtFvlNELkCDLk^7EfwQAfwZyru7xCs7xhp7xRlQyZjyA5iAD5itG5i4ILjHJolHJio%HJ6q%UA6qYAIrQBBsJCutiEutxFutDGetKHZsWIps%WIhvYHNvQG0wJFfw7Efw" /><g i="2" c="1086" charCode="1086" p="#^WA9pWAbrABesfCgtLDgtfFgtUFesyGcryG9pyG7nUF6meF5lKD5leC5lAB6mWA6nWA9p^mK9pmKusBInuRGfwIDfwKBfweAovKyxuWxWs7xir7x9p7xPlSyYjCA5iND5iLF5ifHYiLIOjyJplmK$mmK9p" /><g i="3" c="1073" charCode="1073" p="#^7xQn7x7jVyHgIAfevECdlGhd$JOc%qK2gRIegOEQggD4hvCzhLB2inBYi$ASjWAml%6BmlLBmkPCQjTDhj5FhjDHhj0JQkqKnmqKfpqKAsEIquTGfwLDfwDAfwTy0u7xMr7xQn^ZDetCGetCGApCG1mdE1mzD1mVClmgCEmJB8naBDnWA7oWACqIBWrvCetZDet" /><g i="4" c="1093" charCode="1093" p="%^LA1pmwmiAAmidDImVFmi7KmiHF1pkK$v5G$vdDkrlA$v7w$v" /><g i="5" c="1076" charCode="1076" p="%^vGhtvG9lID9l#pDqnTCtp#lCvroBht^eMUAUIUAUI$vIz$vIzUAmwUAmwhtvxht#GytrtzIo#gAWlAAmieKmieKhteMht" /><g i="6" c="1080" charCode="1080" p="%^yBmiyBLn#yBCohBWrzHmi2Mmi2M$vsI$vsIzq#sI6pHIsmqC$vYx$vYxmi" /><g i="7" c="1084" charCode="1084" p="#^9P$v%GL$v%GLfl%uL$lQKAoiKVp%TH$v%eF$v%NCRpfCwoFB4m%qBfl%qB$v%Yx$v%Yxmi%4Dmi%qFaoOF7p6GlqqGzrxGqsWGBq8HOpnH$oEHkoWHFn4Kmi%9Pmi" /><g i="8" c="32" charCode="32" p="#" /><g i="9" c="1090" charCode="1090" p="%^fJmifJ9lNE9lNE$v2B$v2B9lAw9lAwmi" /><g i="10" c="1074" charCode="1074" p="#^zKXlzK1nSJPnaJAoQHOo%QHUohJ3p7KUp_KJq_KWr_KVtqJYuSH$vYE$v%Yx$v%Yxmi%YEmiMHmi9JgjzKakzKXl^7HKr7HWqvGzqTFcqEEcq%GBcq%GBqt%IEqtUFqtvG_s7Hxs7HKr^NGdmNG_kOE_k%GB_k%GBGn%nEGnzFGnaGknNG_mNGdm" /><g i="11" c="1100" charCode="1100" p="#^GBDn%iEDnsHDnZIDouKDpuKFruK$vsE$v%Yx$v%Yxmi%GBmi^LGIrLGVq6GzquFcqeEcq%GBcq%GBqt%hEqtLGqtLGIr" /><g i="12" c="1085" charCode="1085" p="%^GBmiGBCnTGCnTGmiBKmiBK$vTG$vTGnqGBnqGB$vYx$vYxmi" /><g i="13" c="1072" charCode="1072" p="#^CG$v%UF9u%OF9uSElvSDOvTCfwgBfwjzfway7v2x$t2xXr2xMpzyKo5AIn9DBn%wFwn%wFWmwFRkoDRkMBRkyzQl%jyjjGA4iyD4ihG4iLHhjdJtkdJVm%dJ$v^wFHp%4EKpsCNpFBkqTASqTAYrTAxtGCxtZDxtKEOswF2swFPq" /><g i="14" c="1087" charCode="1087" p="%^mKmimK$vDG$vDG9lGB9lGB$vYx$vYxmi" /><g i="15" c="1088" charCode="1088" p="#^sFfw2DfwGBvu%uBvuGBcwGBuw%GB$B%Yx$B%Yxmi%_Ami%vB7k%GB7k_C5iyF5iZH5ikJZjIKQlIK9pIKlr3KYsqJzueIpv2HfwsFfw^mE4lZC4lkCXlIBNmGBKo%GB7pGBkrkChs_CetpEetVGetVG6pVG5nhG5mGF4lmE4l" /><g i="16" c="1089" charCode="1089" p="#^vDfw7xfw7xfp7xMlSyXjBA5iQD5icG5i4I0j%_GVl5GylkFklAE5lQD5lWA5lWAdpWAetQDetVEetPFYsKGFsFH2s%FHevLGPvQF1wVEfwvDfw" /><g i="17" c="1082" charCode="1082" p="%^VGmi0LmiBFVouL$vgH$vGB4pGB$vYx$vYxmiGBmiGB_o" /><g i="18" c="1081" charCode="1081" p="#^yBmi%yBLnyBCohBWr%zHmi%2Mmi%2M$v%sI$v%sIzqsI6pHIsm%qC$v%Yx$v%Yxmi^YKtcJKLedJOfKHRgXERg1CRgEARfgzRe5ztc%qCtcwCKd2DfeBDLe$ELeeGLeQGberHDdAHtc" /><g i="19" c="46" charCode="46" p="#^qxfuqxdtZxIsxyasAzasBAas8BJsIBftIBfuIBdv8BNvAAkwAzkwyykw_xNvqxevqxfu" /><g i="20" c="1042" charCode="1042" p="#^fy9e%OD9eBH9ejJef1Ljg1LGi1LgkhKilxJjmhIxm%hIEm_J1nKK3ouL5puLQquLgtJJEuYH$vWE$v%fy$v^1Cdl%eEdlMFdlsGLk8Hgk8Haj8H8ioGIhEFfh0Efh%1Cfh^1Cdo%1CTs%vETs3GTsOGhsyHGryHrqyHdonEdo" /><g i="21" c="1103" charCode="1103" p="#^1A$v%$v$v%GzCqmy3qGx1p$w_n$wAm$wCkuyujZzmixCmi%TImi%TI$v%9F$v%9FWq%6DWq^FACmFAsnjBXn_Bqo4Dqo%9Fqo%9F_k%BC_kHB_kaBrlFATlFACm" /><g i="22" c="1083" charCode="1083" p="#^aK$v%sG$v%sG9l%0D9lDCKp3C_rvBeuzAfvEzfw7yfwQwfw$vSv%$vTsBw7tcx7tUx7tmy7sQy7rczOoAzsmRzmi%aKmi" /><g i="23" c="1078" charCode="1078" p="%^bF_obFmiEImiEI_ovNmimRmikMVoQR$vRN$vEI4pEI$vbF$vbF4p_z$v$v$vvBVotwmikAmi" /><g i="24" c="58" charCode="58" p="#^qxfuqxdtZxIsxyasAzasBAas8BJsIBftIBfuIBdv8BNvAAkwAzkwyykw_xNvqxevqxfu^qxakqx8jZxDixy5iAz5iBA5i8BEiIBajIBakIB9l7BIlzAfmAzfmyyfm_xJlqxalqxak" /><g i="25" c="1055" charCode="1055" p="%^mM$vBI$vBIjh1Cjh1C$vfy$vfy9emM9e" /><g i="26" c="1094" charCode="1094" p="%^SKhtRMhtRMUAvJUAvJ$vYx$vYxmiGBmiGBct7Hct7HmiSKmi" /><g i="27" c="1099" charCode="1099" p="#^GBDn%tDDnBGDn5IDoBJDpBJFrBJPt5IVuBG$vCD$v%Yx$v%Yxmi%GBmi^TFIrTFVqeFzqCEcqlDcq%GBcq%GBqt%oDqtTFqtTFIr^iP$v%AL$v%ALmi%iPmi" /><g i="28" c="44" charCode="44" p="#^CBntZARvszdz%MwdzzxZv$x5t%qB5t" /><g i="29" c="63" charCode="63" p="#^nz4q%nzapnz$nTz8nnAgmIBhl_CnkoDOjODdjODwiODJhcDjhDCUgABUgLzUgpx5i%4wqfOyUdRBUdmEUdRF6fkHjgkHkikHGjJGFk6GDloERmdDInVC9oCCCoCClp%CC4q^_yfu_ydtxzIs4Aas7Bas8CasHCJsfDftfDfufDdvHCNv7Ckw7Bkw5AkwxzNv_yev_yfu" /><g i="30" c="1044" charCode="1044" p="%^7wRsvxRs#gzjpiANl#kBfiQB9eeM9eeMRsCORsCOcBYKcBYK$vMz$vMzcB7wcB^QEjh#rE6kxDen#DClquBRssIRssIjh" /><g i="31" c="1079" charCode="1079" p="#^lBCnsDCnkEgndFWmdFamdFwlAEblXDSkrCSkvBSkjA5l7zkl8yJl%2x7jvyAiSzlieB5iWC5itF5i$G4jyI2kyIJlyI1oQFKo%QFSovHgpcI1qWIOqWI1sWIgt6IeujHcvNFKvgEfwcCfwNyfwYwpv%Ywks$xPsfz5tvAntGBntuDntoEZsiFzsiFPriF_qlEBqoDbqqBbq%_zbq%_zCn" /><g i="32" c="1052" charCode="1052" p="%^PF$vvB$hoB$h#DBgmDBInDB$vfy$vfy9epD9eDHOrIHOrbM9ekR9ekR$vON$vONyn#ONYmPNam#RNol_N1iTN1igJ$v" /><g i="33" c="1102" charCode="1102" p="#^OQ9pOQws5PoupNfwpKfwIHfw4GKutEdt7Enq%GBnq%GB$v%Yx$v%Yxmi%GBmi%GBCn%aECnxE$kbGyjSH5itK5inN5i4P$jOQUlOQ9p^TH9pTHcrtIes4JgtsKgtPLgtpMes$Mcr$M9p$M6noM6mOL5lqK5l4J5ltI6mTH7nTH9p" /><g i="34" c="53" charCode="53" p="#^vDCk4GCkCH3m8Jwn8J2q8J1tiHEusFfw1Cfw2zfwdxhv%dx1sbyystzTsLAbtUBbtlFbtlFmqlFFnMBFn7BFnlANnzzVn4z3o%Axfn%fy9e%WH9e%WHmh%yBmh%dBSk%FBNkoCCkvDCk" /><g i="35" c="48" charCode="48" p="#^nJ4nnJLrRH$tjGfw7Dfw2AfwtyXtVwCrVw4nVwmiqy7gYzTd7DTddGTdOHdgnJzinJ4n^FA4nFAmqdBNrNBct7DctrEct0FMrCFkqCF4nCFOj0FmirEWg7DWgOBWgdBmiFAOjFA4n" /><g i="36" c="43" charCode="43" p="%^OBxo4xxo4xSlOBSlOB5htE5htESlbJSlbJxotExotEetOBet" /><g i="37" c="126" charCode="126" p="#^XzOngzOnvydoKxDo4xip%4xtmky7lcA7l5B7lTBklFCwlADVl9FBmlGBm$GBmMHcmxIOlbJ5l%bJWnYHgp3GgpgFgpxE6pODXoICuo5BOnXzOn" /><g i="38" c="49" charCode="49" p="%^kG$vyC$vyCGlBC_jFC7i#JB3jlBmjiz$ktxKidD9ekG9e" /></glyphs></font><font id="10" name="Open Sans Charset1_ 6UoSynS34nV"><glyphs><g i="0" c="1054" charCode="1054" p="#^XN3nXNlrMLOtCJfwLFfwPBfwGzRtxxqrxx1nxxGiGzhgQBTdNFTdDJTdNLkgXNMiXN3n^Jz3nJzHqgBzsPCruLFruJIrueKAsLLIqLL3nLLsjeKBhKIKfNFKfPCKfgBChJzujJz3n" /><g i="1" c="1050" charCode="1050" p="%^iL$vNI$vxAYmxA$vsy$vsy9exA9exAOmAI9eYK9e3DQm" /><g i="2" c="1044" charCode="1044" p="%^xMFAyKFAyK$v9y$v9yFAawFAaw7uyx7u#rzZqMArm#6CVhfC9egK9egK7uxM7u^bI7ubI1g7E1g#VD_iEC7n#oBgrJz7u" /><g i="3" c="1072" charCode="1072" p="#^nG$v%ZF5u%TF5uTEmvTDPvUCfwoBfwpzfwgyev8xcu8xjs8xfoDD3o%VF_n%VF9nVFAldFQkyE4k3D4koB4kgz6l%FyyjEz0jPAJi$BpiaDpiAFpiJGtjTHxkTHTm%TH$v^OBAuHDAuMEytSFvsSFDq%SFqp%QDvppBBpkAgqgzWqgzksgzrtXz0uCAAuOBAu" /><g i="4" c="1053" charCode="1053" p="%^$L$vWJ$vWJCnxACnxA$vsy$vsy9exA9exALlWJLlWJ9e$L9e" /><g i="5" c="1077" charCode="1077" p="#^ODfwQAfw6zsupxEspxqppxbm$yhkBAnihDniOFnifH1kJIHlJIoo%JIGp%vzGpzz1sHAgtQBuuTDuu1Guu9IAt%9Iov4HRv6G2w9FfwODfw^fD4kEB4kGA7lJzamyz1o%yG1oyG6mHF5lRE4kfD4k" /><g i="6" c="1090" charCode="1090" p="%^aHmkQCmkQC$vOA$vOAmkvwmkvwDiaHDi" /><g i="7" c="49" charCode="49" p="#^KE$v%LC$v%LChjLCIhRChgBCxggCPgYB5hnzcj%iyPh%0D9e%KE9e" /><g i="8" c="32" charCode="32" p="#" /><g i="9" c="1080" charCode="1080" p="%^2ADi2A6rZzktXz0uaHDiIJDiIJ$vOH$vOHQnRHdmVHDkGA$v8y$v8yDi" /><g i="10" c="1079" charCode="1079" p="#^IAaovEaovE4mvE5kqB5kuA5kIzgkXyrkIxYk%_wij2znivBniPDni8FkjuGgkuGVluG8oZDRo%ZDXowFopdGeqXG3rXGksXGburFdvXDfwiBfwpyfwQwov%Qwxt3zAulBAu6DAu$DZtVEmtVEesVEUp6BUp%fzUp%fzao" /><g i="11" c="51" charCode="51" p="#^hIlihI3kjH9lmGemCECm%CEImLGZmNH4oQIapQIYqQIvt3HTuiFfw1CfwCAfwrz1wgyQv8xhv%8xmtjyXtDzeuXAxu6CxuKGxuKGVqKGFnDBFn%TzFn%TzVl%FBVlKDVlYE_kbG3kbGqibG6hhFngoEDfRCDfGBDfEAYfCzgggy6h%fxLflyTeNzoedBUdOCUdpFUdRG5fhIhghIli" /><g i="12" c="1055" charCode="1055" p="%^ML$vHJ$vHJ$fxA$fxA$vsy$vsy9eML9e" /><g i="13" c="1086" charCode="1086" p="#^HJipHJAs1IquoGfwuDfwIBfwjApvWyzu9y_spxprpxippx1m1zckGAniADnioGni1IfkHJ6mHJip^vzipvzSrwActyByuyDyuxFyuzGdtBHTrBHipBHLmzGqlxF5kwD5kxB5kwAplvzImvzip" /><g i="14" c="1083" charCode="1083" p="#^7I$v%3G$v%3Gmk%2CmkJBIo7BfryAOtCz_uHyawfxawBwawbw1w%bwwutwBuPwBucyBu1zErTzGoiADi%7IDi" /><g i="15" c="1085" charCode="1085" p="%^aADiaAdoGHdoGHDiIJDiIJ$vGH$vGHZpaAZpaA$v8y$v8yDi" /><g i="16" c="1091" charCode="1091" p="#^1wDi%cyDi%7Bfq5CSskC0u%qC0uACot4DUrBDoqoGDi%zIDi%QCSxZB6AQA2BHz$B1y$B5x$BbwOB%bwaASwjAIxjANzjAGAZx%qB3w" /><g i="17" c="1102" charCode="1102" p="#^nPipnPBsONqueMfwvJfwVGfwnFDuRD_sHDZp%aAZp%aA$v%9y$v%9yDi%aADi%aAdo%IDdoYDrluFVj1HniyJnieMniONeknP5mnPip^NFipNFTrGGdtzHyuxJyusLyumMfthNYrhNiphNKmoMqlvL5kxJ5kzH5kGGqlNFKmNFip" /><g i="18" c="1089" charCode="1089" p="#^vDfwBAfw$ytupxGspxoppx1m0zckEAniDDniBEnizFBixGOi4H4j%sGOkNFxk_EmkbEakADakvzakvznpvzRrvAatvBuusDuu7FuuTGMt%TGzvxFfwvDfw" /><g i="19" c="1088" charCode="1088" p="#^nEfw3Dfw_BMvVAhvaAhu%1AhuaAsvaAvw%aA$B%8y$B%8yDi%OzDi%4Ask%aAskYAmj_BTi1DninEni1HnitIckWJ0mWJipWJBssIqu_GfwnEfw^4E5k1C5k6BelcAmmaARo%aAipaA6s6Bkt2Cyu7EyuSFyuRG8tQHKrQHgpQHMmRGrlSF5k4E5k" /><g i="20" c="1082" charCode="1082" p="%^XFDi9IDioC4pEI$vgG$vaAepaA$v8y$v8yDiaADiaA7p" /><g i="21" c="1084" charCode="1084" p="#^5F2u%tFVs%$Ftr%DJEi%cMEi%cM$v%pK$v%pKYk%9KFl%sJxn%$F$v%iE$v%RAvncASlYzYk%Yz$v%9y$v%9yEi%DAEi%7E7rFEts5F2u" /><g i="22" c="1087" charCode="1087" p="%^aA$v9y$v9yDinJDinJ$vkH$vkHokaAok" /><g i="23" c="83" charCode="83" p="#^wIfrwICtPGXu6FfwaCfw$yfwixrv%ixrtoyVtHzau_ArufCrukErunFFtqGSsqGsrqGwq2GXpGFlpOERoXDko9CInFzPmByBlxxmkxxoixxkg4z6fDAUdaDUdRFUd4ITe%qHGgdFLf7DLfuBLfyAtgDzahDzqiDzljZzXjjAxk7B1lXBxlCD7mpG7nsHhowIqpwIfr" /><g i="24" c="104" charCode="104" p="#^iH$v%iHmniHJlyGWkPF6keE6k6C6k8BglaApmaA0p%aA$v%9y$v%9y$c%aA$c%aALiaAOj4Auk%cAukOAwjUBZi$CpiqEpiTGpi5IAjkJKkkJhn%kJ$v" /><g i="25" c="101" charCode="101" p="#^ODfwQAfw6zsupxEspxqppxbm$yhkBAnihDniOFnifH1kJIHlJIoo%JIGp%vzGpzz1sHAgtQBuuTDuu1Guu9IAt%9Iov4HRv6G2w9FfwODfw^fD4kEB4kGA7lJzamyz1o%yG1oyG6mHF5lRE4kfD4k" /><g i="26" c="108" charCode="108" p="%^aA$v9y$v9y$caA$c" /><g i="27" c="1078" charCode="1078" p="%^fEEi7GEi7G7pELEiSNEihI7plO$v$L$v7Gdp7G$vfE$vfEdpny$v2w$v6C7pxwEiLyEifE7p" /><g i="28" c="1100" charCode="1100" p="#^aA9o%iE9oqJ9oqJWrqJVt4IYuLG$vbE$v%9y$v%9yDi%aADi^aAVp%aAiu%4EiuHFiuyGKtpHatpH2spHXqCGqqQFVp0EVp" /><g i="29" c="1092" charCode="1092" p="#^uMipuMlsLK9u1JYvWFcw%WF$B%WD$B%WDcwUAZv7z7unxhsnxipnxgm7ztkUAGi$Dqi%$D$c%WF$c%WFqi_IIiKKykuMnmuMip^vzipvzFrAA_sFBju$Dxu%$D7kKBkkCABlvzSmvzip^oKipoKDkWF9k%WFxufIiujJZsoKEroKip" /><g i="30" c="1094" charCode="1094" p="%^cLDAaJDAaJ$v9y$v9yDiaADiaAfuhHfuhHDijJDijJfucLfu" /><g i="31" c="1081" charCode="1081" p="#^2ADi%2A6r%Zzkt%Xz0u%aHDi%IJDi%IJ$v%OH$v%OHQn%RHdm%VHDk%GA$v%8y$v%8yDi^TDRgDBRgAAZfyz5fqz5d%kB5drBme_BSeyCmfWDmfbFmfNFQeoGiewG5d%rI5diI1fcHXf7GRgTDRg" /><g i="32" c="45" charCode="45" p="%^1xeq1xno0Dno0Deq" /><g i="33" c="116" charCode="116" p="#^tCAu0DAuwDvu0EquiEku%iEUvZD2wkD8wHCfwaCfwiyfwiy9s%iyck%nwck%nwej%iyoi%9zxf%kAxf%kADi%cEDi%cEck%kAck%kA4skAhtUAXttBAutCAu" /><g i="34" c="112" charCode="112" p="#^nEfw3Dfw_BMvVAhvaAhu%1AhuaAsvaAvw%aA$B%8y$B%8yDi%OzDi%4Ask%aAskYAmj_BTi1DninEni1HnitIckWJ0mWJipWJBssIqu_GfwnEfw^4E5k1C5k6BelcAmmaARo%aAipaA6s6Bkt2Cyu7EyuSFyuRG8tQHKrQHgpQHMmRGrlSF5k4E5k" /><g i="35" c="115" charCode="115" p="#^NGmsNGduoFev$DfwuBfwPyfwkxpv%kxwtiy0uoziuvAAuxBAu6DAuZD4uQEztQExsQELr8EbrtDDqvBTpEzapRyFo3y8oGxunixQmixVlixgkDykjYznigCnirEnivGfj%NFVkMD4k7C4kHA4kYzxkdz_kdzMldzjmuzHmMz3nnApn_ALnJCoo6FgpXF8qNG0rNGms" /><g i="36" c="58" charCode="58" p="#^SxIuSxUtdyttBy2tiz2t$z2toAttOAUtOAIuOAvvoAXv$zmwizmwGymwgy_vSxBvSxIu^SxXjSxhiizhiOAhiOAXjOAJkoA9l$zAlizAlGyAlgyclSxPkSxXj" /><g i="37" c="47" charCode="47" p="%^XE9egy$vfw$vVC9e" /><g i="38" c="119" charCode="119" p="%^4J$vDG9o#oGrnLFTkFFTk#aF0nPEaohC$vXz$vhwDipyDi#IzGnnAjq#3BXs9BStfBSt#oB9tHB3s#_BYqcCiqFEDiSGDifJiq#XJpsaKQthKQt#kKotxKus#LKzr4NDibPDiuL$v" /><g i="39" c="46" charCode="46" p="#^SxIuSxUtdyttBy2tiz2t$z2toAttOAUtOAIuOAvvoAXv$zmwizmwGymwgy_vSxBvSxIu" /><g i="40" c="99" charCode="99" p="#^vDfwBAfw$ytupxGspxoppx1m0zckEAniDDniBEnizFBixGOi4H4j%sGOkNFxk_EmkbEakADakvzakvznpvzRrvAatvBuusDuu7FuuTGMt%TGzvxFfwvDfw" /><g i="41" c="111" charCode="111" p="#^HJipHJAs1IquoGfwuDfwIBfwjApvWyzu9y_spxprpxippx1m1zckGAniADnioGni1IfkHJ6mHJip^vzipvzSrwActyByuyDyuxFyuzGdtBHTrBHipBHLmzGqlxF5kwD5kxB5kwAplvzImvzip" /><g i="42" c="109" charCode="109" p="#^cP$v%cPincPHlwOUkQN5koM5kvK5kBJblHIgmHIxo%HI$v%GG$v%GGinGGHl_FUkiF5kRD5kXB5k2BelaAnmaA_o%aA$v%8y$v%8yDi%OzDi%7Ask%dAskOAtjRBWiUCniaEnijHnihIFk%nIFkZIBj6K_ifLniIMniZOni5QyjdRIkdRgn%dR$v" /><g i="43" c="97" charCode="97" p="#^nG$v%ZF5u%TF5uTEmvTDPvUCfwoBfwpzfwgyev8xcu8xjs8xfoDD3o%VF_n%VF9nVFAldFQkyE4k3D4koB4kgz6l%FyyjEz0jPAJi$BpiaDpiAFpiJGtjTHxkTHTm%TH$v^OBAuHDAuMEytSFvsSFDq%SFqp%QDvppBBpkAgqgzWqgzksgzrtXz0uCAAuOBAu" /><g i="44" c="98" charCode="98" p="#^nEpi$GpisIckWJ$lWJipWJBssIqu_GfwnEfw3Dfw_BMvVAhvaAhu%1Ahu%Bz$v%8y$v%8y$c%aA$c%aADhaAaj4Apk%aApkBBpinEpi^4E6k$B6k4BilaAumaAipaA7s6Blt2Cyu7Eyu$FyuVGbtQHQrQHhpQHGmVGol$F6k4E6k" /><g i="45" c="117" charCode="117" p="#^2ADi%2Air2AXsOALtyByu7DyueFyucGptaHfsaHFp%aHDi%bJDi%bJ$v%wH$v%eHdu%7HduvGcvoFKvhEfwTCfwrAfwdz5v$xXt$xnr%$xDi" /><g i="46" c="114" charCode="114" p="#^fEni8FniRFwi%zFpkKEdk6EdkuCdkkBylaASmaAQo%aA$v%8y$v%8yDi%PzDi%2A5l%9A5lUAOjXB5j$CnifEni" /><g i="47" c="105" charCode="105" p="#^aA$v%9y$v%9yDi%aADi^_x$e_xiejy_dFyFdazFdFzFd0A_dnAjenA$enAHf0A1gFzmgazmgFymgjy1g_xHf_x$e" /><g i="48" c="103" charCode="103" p="#^6JDi%6JVj%DGckZGDkeHjlvH$lvHTmvHQo9G$pPEartCarTBarlB4r2AMr2AOs2AltvACtYATt3CTt%qETtBGTtMHOuXIIvXIsxXIGz9HQAnF$BYB$Bkz$BUx0Btw2Atwgytw2xfx9w2ygvszYuXyJuByeufyKtfy5tfymsEyPr1zgrTzLqQyjqayipxxgoxxYmxxLkRyzjaAniACniEDnitEDi^qyeyqykzlzUzgAsAZBsAxEsALFHz_GWy_GDx_GxwjG6wEFHvNDHv%lBHvZzHvbzlwqy$wqyey^xzVmxzjojA1p6BLpxCLpvFLpvFTmvFSjvCSj3BSjiADkxzolxzVm" /><g i="49" c="110" charCode="110" p="#^iH$v%iHlniHIlyGVkPF5keE5k7C5k8BelaAmmaA_o%aA$v%9y$v%9yDi%OzDi%7Ask%dAskRAtjZBWi5DnitEniUGni6IyjkJIkkJgn%kJ$v" /><g i="50" c="121" charCode="121" p="#^1wDi%cyDi%7Bfq5CSskC0u%qC0uACot4DUrBDoqoGDi%zIDi%QCSxZB6AQA2BHz$B1y$B5x$BbwOB%bwaASwjAIxjANzjAGAZx%qB3w" /><g i="51" c="1047" charCode="1047" p="#^PIkiPI5kHHblAGhmCEAm%CEGmRG_m$H5o9Jbp9JYq9JsthHSuqFfw$BfwUyfwVwhv%Vwmt4yWtrzeuOAxu3CxutExuIFDtYGIsYG_qYGlpAFvocEFnuBFn%QyFn%QyVl%nBVlTDVlfF0lDG6kDGviDGbhDFpgEEDfZCDfDBDfxAXfszeg1y8h%$wLfeyQeMzmeiBUdYCUdIFUdfH5fPIigPIki" /><g i="52" c="92" charCode="92" p="%^gy9eYE$vWC$vhw9e" /><g i="53" c="1052" charCode="1052" p="%^mG$viAbgcAbg#nA3inAFknA$vsy$vsy9eAB9eeHTskHTs1N9e8Q9e8Q$v3O$v3Ovk#3OxieOcg8Ocg1I$v" /><g i="54" c="1074" charCode="1074" p="#^$I_l$IinfIZnvHEo8GTo%8G_oRHdpDI_pqJLqqJ6sqJZt2I_uGG$v2E$v%8y$v%8yDi%0EDi$IDi$I_l^pHZrpHUqAGpqLFVpRDVp%aAVp%aAiu%UDiupHiupHZr^0Hbm0HclgGOkwFok$Dok%aAok%aA9o%CD9ouF9ofGIn0Hen0Hbm" /><g i="55" c="1103" charCode="1103" p="#^Py$v%sw$v%iAlqLy0qWx1p5x2o5xzm5xJkkyGjzzDiMBDi%KHDi%KH$v%IF$v%IFFq%kCFq^4zAm4zUorCUo%IFUo%IFok%1Cok4zok4zAm" /><g i="56" c="1096" charCode="1096" p="%^7Ifu2Ofu2ODi6QDi6Q$v8y$v8yDiaADiaAfu5Gfu5GDi7IDi" /><g i="57" c="1042" charCode="1042" p="#^sy9e%vD9e2H9eDIdfdKhgdKAidK9kkJclsIemLGxm%LGFmQKlnQKWqQKjtcJFuBH$vHE$v%sy$v^xAOl%YDOl8GOl6H6l4Iqk4INi4Ihh$GDgWFYfADYf%xAYf^xAzn%xAeu%fEeuqGeuvHptBIzsBINqBI7ptHlomGzn4Ezn" /><g i="58" c="1099" charCode="1099" p="#^aA9o%QD9onG9oBH6pQI2qQIWrQIXtxHZueG$vID$v%9y$v%9yDi%aADi^5N$v%4L$v%4LDi%5NDi^aAVp%aAiu%CDiuQGiuQG2sQGWq4GqqlFVpyDVp" /><g i="59" c="1093" charCode="1093" p="%^nB9pJwDi1zDiyCLn3GDilIDiID9pBI$viG$vyCAqMy$vtw$v" /><g i="60" c="1076" charCode="1076" p="%^MJDAPHDAPH$vsy$vsyDAvwDAvwfuyxfu#bz1s6A2p#2B2m4BDiSHDiSHfuMJfu^VFfuVFdkUCdk#KCWmRBIp#ZAusFzfu" /><g i="61" c="1097" charCode="1097" p="%^7Ifu2Ofu2OEi4QEi4Qfu$Rfu$RCAXPCAXP$v8y$v8yEiaAEiaAfu5Gfu5GEi7IEi" /><g i="62" c="1064" charCode="1064" p="%^mT$vsy$vsy9exA9exA7uSH7uSH9eXJ9eXJ7ugR7ugR9emT9e" /><g i="63" c="1056" charCode="1056" p="#^MJmjMJ3mVHxn3G_oDC_o%xA_o%xA$v%sy$v%sy9e%4D9eMJ9eMJmj^xAcn%oCcn9FcnoGjmDHqlDHsjDHHhsGQgiFYfRCYf%xAYf" /><g i="64" c="8470" charCode="8470" p="#^WK$v%EI$v%cA0h%5A0hiAxkiASl%iA$v%sy$v%sy9e%QA9e%8J4t%eJ4t3J4q3Joo%3J9e%WK9e^fUqofUpqgTxrhSFsuQFsOOFsONwrPMnqPMqoPMqmONklNOdkAQdkgSdkfTmlfUvmfUqo^qOqoqOPpVOxqpPfrxQfrFRfr7SyqCSQpCSqoCS0n7SkmFRElxQElqPElWOkmqO0nqOqo^mN$v%mNmu%CTmu%CT$v" /><g i="65" c="1058" charCode="1058" p="%^YD$vTB$vTB$fdw$fdw9eBJ9eBJ$fYD$f" /><g i="66" c="50" charCode="50" p="#^YI$v%dx$v%dxfu%WBxp4EmnLErmrFvlNFDk7GKj7GJi7GihfFtgoEDfRCDfKBDfKA$fLzmgxykh%sxXfWzUdQCUdlFUdMGbfcItgcIEicIlkfH$liGFnGDcq%Mz1u%Mz7u%YI7u" /><g i="67" c="33" charCode="33" p="#^_z4r%Iy4r%4y9e%BA9e^SxIuSx2tjz2t1A2tpAutOAVtOAIuOAuvpAWv0AmwjzmwHymwgy_vSxBvSxIu" /><g i="68" c="1073" charCode="1073" p="#^sx_nsxAjLy7h2AFeRC2elGjd$IRc%nJDe8FkfkDLfzB9gGAFhNz9jIzLl%RzLlCAJkOB8k$CyjiEyjMGyj8I9lxJLmxJApxJJsWHuukGfwtDfwFAfw2z5usxWrsx_n^FDyunHyunHOpnHgl$Dgl3DglcCFllB1mDAGmWzjnxz_nxzbryATszByuFDyu" /><g i="69" c="89" charCode="89" p="%^$C4nLH9e$J9e2E4p2E$vXB$vXBap$v9egy9e" /><g i="70" c="80" charCode="80" p="#^MJmjMJ3mVHxn3G_oDC_o%xA_o%xA$v%sy$v%sy9e%4D9eMJ9eMJmj^xAcn%oCcn9FcnoGjmDHqlDHsjDHHhsGQgiFYfRCYf%xAYf" /></glyphs></font><font id="20" name="Gilroy ExtraBoldBold Charset1_ 6lYIdmTy2AI"><glyphs><g i="0" c="1048" charCode="1048" p="%^fH$vfL$vfLvefIvevB$nvBvevxvevx$vvA$vfHvm" /><g i="1" c="1089" charCode="1089" p="#^nDlweFkwJGtvcICu1J7t%LFfrrFVrOEhs9EEskDFs4CDsiBRrxA3rvALpxAroiBFn4CTmkDRm9ESmNEenqFBnLFfo%1JlmbIUkIG1kdFajnD9jsBajZz1kuyUkDxomMwTnLwLpMwDrDx7tuyCuZztvsBkwnDlw" /><g i="2" c="1090" charCode="1090" p="%^vHvjfwvjfw5n1A5n1A$vND$vND5nvH5n" /><g i="3" c="1086" charCode="1086" p="#^nDlweFkwJGtvdICu5J7t_JDr$JLp_JTn5JomdIUkJG1keFajnD9jwBaj0A1kxyUkExomMwTnLwLpMwDrEx7txyCu0AtvwBkwnDlw^nDIs7CHskBUrxA5rvALpxApokBCn7CPmnDOmDEPmqFCndGpofGLpdG5rqFUrDEHsnDIs" /><g i="4" c="1088" charCode="1088" p="#^RE9jBD9jGCzjLBYj7BGk%7Bvj%nxvj%nx$A%7B$A%7BQuLByvGCYvBDlwRElwvGkwRHtvcJCu$J7tPKDrQKLpPKTn$JomcJUkRH1kvGajRE9j^5EOsNCNsZB_r9Bar7BLp9BkoZBxnNCJm5EImqFJmeGxn2Hko4HLp2HareG_rqFNs5EOs" /><g i="5" c="1080" charCode="1080" p="%^nGvj1BLp1Bvjnxvjnx$v7A$vtFLptF$v7J$v7Jvj" /><g i="6" c="1103" charCode="1103" p="#^LHvj%FBvj8Awj5zak3yPkxxQl$wQm$wYn$w8pDxcqfygrqzTr%vw$v%LA$v%kDps%5Eps%5E$v%LH$v^ZBOm%5EOm%5Eip%ZBipnBip0B_oFAFoFA4oFAtn0B8nnBOmZBOm" /><g i="7" c="32" charCode="32" p="#" /><g i="8" c="1078" charCode="1078" p="%^$O$vRKLpLOvjBKvjsHRosHvjODvjODRoFAvjvwvjpALpfw$vpA$vODAqOD$vsH$vsHAqRK$v" /><g i="9" c="1076" charCode="1076" p="%^TIvsTIvjOyvjOyao#OyMpxyNq#gyOrOxvsfwvsfwlzVzlzVz$vRG$vRGlzvKlzvKvs^JBvs#4CFrgCBq#sCxpsCaosCRmdFRmdFvs" /><g i="10" c="1077" charCode="1077" p="#^JAfr%BJfrLJxqLJLpKJRnVImm5ITkFG1keFajpD9jpBajVz1kqyUkBxomMwTnLwLpMwDrBx7tryCu_ztvxBkwGDlwsFlwQGIvcI2v7JNt%7G2sLFts7FKsvE_sJD$sHC0tUBDs5BdsJAfr^FAsoWAunCB_miCumnDtmeEtmZEWmIFnn1Gso" /><g i="11" c="1085" charCode="1085" p="%^nFvjnF$n7B$n7Bvjnxvjnx$v7B$v7BvrnFvrnF$v7J$v7Jvj" /><g i="12" c="1082" charCode="1082" p="%^nJ$vIELpfJvjTEvj7BZo7Bvjnxvjnx$v7B$v7Btq7F$v" /><g i="13" c="1084" charCode="1084" p="%^DKvj1Hvj$DdoZAvjnxvjnx$vZA$vZAypNDVtdEVt1Hyp1H$vDK$v" /><g i="14" c="1087" charCode="1087" p="%^7Jvjnxvjnx$v7B$v7B$mnF$mnF$v7J$v" /><g i="15" c="1072" charCode="1072" p="#^sGvj%sGGkQFYjVEzj_D9jJC9j3BajJz1knyUkzxomMwTnLwLpMwDrzx7tnyCuJztv3BkwJClw_DlwVEYvQFyvsGQu%sG$v%cK$v%cKvj^tDOs9CNslB_rxAarvALpxAkolBxn9CJmtDImOEJmCFxnqGkosGLpqGarCF_rOENstDOs" /><g i="16" c="83" charCode="83" p="#^DDlwyFlw$GIvsI3vhJTt6KGs7KZq5K9pfJ6oqI2n8HumSFWlvEyl9D8ltCOkOBskzB6kkBMjlBnjlBQiPBsihC3idD2ipE3i6FBiPF7jfG4k%DJ5iFI9g0H9foF9edD9eHB9emANe1zpfcyBgnxNhlxtjnx8l6ybmRyen$zRnaBsovCOosEjpiFNp8Gfq7G1r9GzrEF$r8FqsLDsshCrspBNrxA7r4A1q%Dw1smx_t6z9vTAkwDDlw" /><g i="17" c="72" charCode="72" p="%^$Gve$GclvBclvBvevxvevx$vvB$vvB2p$G2p$G$v$K$v$Kve" /><g i="18" c="69" charCode="69" p="%^vB9svB2pLH2pLHflvBflvBlinIlinIvevxvevx$vvI$vvI9s" /><g i="19" c="76" charCode="76" p="%^vB9svBvevxvevx$vLH$vLH9s" /><g i="20" c="1044" charCode="1044" p="%^fL9sfLvexzvexzlm#wzzo8zXp#Myjr9y9snw9snwlznAlznA$v7J$v7Jlz7Nlz7N9s^pC9s#TCkrbDXp#wDyoxDpmxDfifHfifH9s" /><g i="21" c="1054" charCode="1054" p="#^RFlwoIkwrK8vvMYtINVrWORpYOfnWOFkINCivMygrKmfoIaeRF9ejDaefBmfczyg_xCiNwFkLwfnNwRp_xVrczYtfB8vjDkwRFlw^RFsspErsfDOr6C9rrB$pMAQoLAfnMAGlrBwk6CljfDIipE3iRF2iiH3irIIiBJljgKwkXKGlYKfnXKQogK$pBJ9rrIOriHrsRFss" /><g i="22" c="1041" charCode="1041" p="#^fE$k%vB$k%vBli%LIli%LIve%vxve%vx$v%fE$v2G_voHjvKIEuuJpteKasfKvqeKQouJBnKImmoHHl2G0lfE$k^fEfs%vBfs%vBLo%fELo5FKoFF8peGypfGvqeGsrFFSr5FgsfEfs" /><g i="23" c="1056" charCode="1056" p="#^7Eve%vxve%vx$v%vB$v%vBvq%7EvqTFuqfHHpDIUoqJyneKbmfKvkeKPiqJthDI6gfHjfTFwe7Eve^7ELm%vBLm%vBfi%7Efi3FgiEFUieGwjfGvkeGulEF6m3FKm7ELm" /><g i="24" c="1055" charCode="1055" p="%^LKvevxvevx$vvB$vvBliLGliLG$vLK$v" /><g i="25" c="1046" charCode="1046" p="%^OS$v9N5nySve7OvexJcmxJvexFvexFcmWAvevwveVB5nfw$vGA$vxFfoxF$vxJ$vxJfonO$v" /><g i="26" c="1040" charCode="1040" p="%^DI$v$M$v2HveYBve$v$vnA$vfBftLHft^sCvpvE4jyGvp" /><g i="27" c="1051" charCode="1051" p="#^fw$vVxcwtzIv2Bcv4CCt6D$r9DVo%9Dli%fHli%fH$v%fL$v%fLve%9zve%9z2p8zvqOyfrsy_rOxcs9xpsfwfs" /><g i="28" c="1042" charCode="1042" p="#^lIWm3JjmtJslTJBkTJvjSJ_h7JSgoIKf8H7fUFwelEve%vxve%vx$v%RE$vrG_vIHmv_IKuKJBtuKrsvKTquKypVJyolJynlIWm^lEfi2FgisFHiSF6jTFOjSFukrFWk1FlllEll%vBll%vBfi^REfs%vBfs%vBVo%REVoCFVo2GnpuGQpvGAquGjr2GNrCFesREfs" /><g i="29" c="1058" charCode="1058" p="%^fJvefwvefwliLAliLA$vLE$vLElifJli" /><g i="30" c="1068" charCode="1068" p="#^7E$j%vB$j%vBve%vxve%vx$v%7E$vTF_vfHbvDIouqJ2teKHrfK$peKjoqJZmDIClfHPkTF0k7E$j^7Efs%vBfs%vBLn%7ELn3FMnEFooeG0pfG$peG_qEFCr3Fes7Efs" /><g i="31" c="33" charCode="33" p="#^$xLp%$ALp%LBvj%LBve%fxve%fxvj^vzlwvAkwaBFvRBZuTBZtRBZsaBisvADrvzBrvyDrQxis9xZs7xZt9xZuQxFvvykwvzlw" /><g i="32" c="1074" charCode="1074" p="#^IGBphHapAHxoTHUnTH4nTHulOGwkJFxjDDvj%nxvj%nx$v%7E$vdGZviH$unI0unIqsnItrXHLqwH1qIGBp^dDvmKDvm0EJmjEXmkEpnjERn0E2oKDfodDfo%TAfo%TAvm^DDVs%TAVs%TA5r%DD5r7E5rqEjrJExrJEZrJErsqEGs7EVsDDVs" /><g i="33" c="1083" charCode="1083" p="%^fIvj2yvj2yAq#2yLrBxfs#8xLsfwvsfw$v#$yjwoA$u#OBGtOBQqOB5nvE5nvE$vfI$v" /><g i="34" c="1100" charCode="1100" p="#^dDfn%7Bfn%7Bvj%nxvj%nx$v%dD$vwFZvPGOu6IDt7IDr6IDpPGsowFhndDfn^fDLs%7BLs%7Bvq%fDvqPDwq8EQqtE7rtEDrtE7s8ErsPDKsfDLs" /><g i="35" c="1053" charCode="1053" p="%^$Gve$GclvBclvBvevxvevx$vvB$vvB2p$G2p$G$v$K$v$Kve" /></glyphs></font><font id="30" name="ArialBold Charset1_ 62H3IkeSRLX"><glyphs><g i="0" c="1048" charCode="1048" p="%^Tx5efB5efB1qvI5e5M5e5M$vJI$vJIikuB$vTx$v" /><g i="1" c="1079" charCode="1079" p="#^hBHq%hBsoaCsozCloZCdokDNnHDknHDLmHD8meDDlOC6lWB6leB6lIAplaAIlKzOm%QwamgxtkIyCj8ALi_BLijELiBFQjUGVkUGxmUGxnkGcoNFToAErp1GQpKGDqsHqrsHBssH6u1GcvDEiwZBiwkxiwiwGs%rz5sbA$tXB$tUC$ttDvt2E_s2Ejs2EyrrD7rRCHqSBHq" /><g i="2" c="1091" charCode="1091" p="#^aw1j%Qz1j%XCes%YF1j%vJ1j%XEwv%6EMxFDVyfDvzRC6AjCtANBRA$A2BeAgBfzgBgygBjx3B%$wnyPxxysyxyFzxydAQxOA7x6B1w" /><g i="3" c="1095" charCode="1095" p="#^ox1j%SA1j%SA8mSAcn2BJneBeoRBCotC_opD_ojE_osFzo%sF1j%UI1j%UI$v%sF$v%sFQqsDmrpCmrQAmrzzHqjy$pRxYooxUnox7m" /><g i="4" c="1080" charCode="1080" p="%^Ix1j$A1j$AbrhG1jFJ1jFJ$vmG$vmGJn$A$vIx$v" /><g i="5" c="1090" charCode="1090" p="%^fw1j$H1j$HOlRDOlRD$vpA$vpAOlfwOl" /><g i="6" c="1100" charCode="1100" p="#^Tx1j%jB1j%jBqo%LEqoNGqoSHJoYI$oGJ_poKYqoKesoK6u5J3vPH$veF$v%Tx$v^jBQt%vEQt$FQtqGltRGRsRGbsRGer6GUqoFxqyDxq%jBxq" /><g i="7" c="1055" charCode="1055" p="%^Tx5e5M5e5M$vuI$vuI5huB5huB$vTx$v" /><g i="8" c="1088" charCode="1088" p="#^Ix1j%VA1j%VAXkxBYjBCmjFDLiXELicHLiMIxklKimlKsplKIsLIvuaHiwWEiwRDiwZCTv6Crv8Bpu%8BXA%IxXA^5Bip5BurYBxsQCAt4EAtgFAt3GDsSGFrSGtpSGrn1GsmdFsl0EslLCslWBqm5Bon5Bip" /><g i="9" c="1086" charCode="1086" p="#^$wlp$wDnRx1mHyrkdABjMBLiGDLiCGLiuIFknKzmnKupnKqstImuAGiwIDiwWBiwiAvvHyHuRx8t$wAr$wlp^wAxpwAsrqBuslCvtHDvt1FvtXFusRGsrRGvpRGBnXFAm1FylHDyllCylqBAmwABnwAxp" /><g i="10" c="1076" charCode="1076" p="%^wI$vIy$vIyqzWvqzWvbtkxbt#cydsNy8q#mz3otz1jWJ1jWJbtjLbtjLqzwIqz^xGbtyGRlpCRl#cCdrHAbt" /><g i="11" c="1083" charCode="1083" p="#^Ky1j%cK1j%cK$v%MG$v%MGPl%7CPl%7CEr7CStCBMu5BFvtAXvSzdwtydwFxdwjw$v%jwttqwttUwvtqxxtJxxtqyxtAy4tKyCsKyxq" /><g i="12" c="1078" charCode="1078" p="#^9D$v%9DtquCwqdCMqZB0riBfs%Gz$v%_v$v%PxqsczKpIAlpAzWo_y8nxyPl9yylNxhlqwhl%qw0jrxYiRxYiZyYiMzsjAAYjiBXlRBunaCUnvCio9Dko%9D1j%zG1j%zGkodHkoyHVnUHtnqIXl7J_jVJtjIKYiXLYihMYiiN0j%iNhlXLhlzLylbLPlKK8n8KWo0JlpwKKpVLqs%KN$v%2K$v%qIfs_HfrCHUqfHwqzGtq%zG$v" /><g i="13" c="1085" charCode="1085" p="%^Fx1j5B1j5BNn$FNn$F1jrJ1jrJ$v$F$v$Fyq5Byq5B$vFx$v" /><g i="14" c="1103" charCode="1103" p="#^VI1j%VI$v%vF$v%vFCq%bFCq4ECqyDVq1DbroC6s%bCns%Wz$v%Xv$v%oyesrzDqiAnqSyiqYxip3xho3xJm3xslFxzkfyGjezmjdA1j9C1j^vFel%1DelHBel7BDlAA$lAAVmAAOncBboQBAofDAo%vFAo" /><g i="15" c="1074" charCode="1074" p="#^Qx1j%kF1jEH1jNITjXJJkXJpmXJvnjJjoHI6pKHnp4JIpKJCqoKwroKBsoK6uhJ3vaI$v$F$v%Qx$v^hBpo%uDpo5FpoOF0owGCnwGKmwGWlRFAlbFeluDel%hBel^hBOt%_DOtsFOt7GstOG5tOGasOGdr1GSqgFvq1Dvq%hBvq" /><g i="16" c="32" charCode="32" p="#" /><g i="17" c="1073" charCode="1073" p="#^wHHd%RJHdKJef1J2gkIRgAFRgfFRgWEQg%uEQgRCQgPBbhOAyh8AAivzCjtzWldAukqBNjDC4jhE4jRG4jCI3lnK2nnKFpnKoswIluFGiwFDiwBBiw1AjvtyjuOxCs7xUq7xWm7xfiQydgyAaePEae%yGaegHaewHHd^CACpCAoruBqsnCstFDst2FstWFosPGjrPGDpPGUnVFRm0FNlIDNlqCNlwBQmCASnCACp" /><g i="18" c="1077" charCode="1077" p="#^iFTr%JIss3IkuEGjvdFiw4DiwIziw4y5uOwjsOwDpOwpmuyAkaALiKCLiEFLijHGk_IAmVIwq%jAwqlA2s8BUsXBKt6DKtWDKttEit0FSsiFTr^vFqotFWmKE9m$DnlYCnlQBnl5BbmmA0nnAqo" /><g i="19" c="1047" charCode="1047" p="#^mA_i%Rwai_xOdiDOdsGOd2IbfFJzgFJriFJJjWILkbINlJGzmwIanpJioiKppiK2riKptzISuRGjwpDjwBAjwZyovlxsuxwUr%RzOqmApscBUs3CmtiDmt0FmtOFDsAGTrAGWqAGQpHF9pOEuo0Duo%bCuo%bCNl%CCNlgENl8F2l0Gik0G3j0G4iiFphBEKggDKg$AKgmA_i" /><g i="20" c="1072" charCode="1072" p="#^mA$m%fxrmNxzk3zFjlALiTCLiaFLihGijpHRjSHGkkIvlkIKn%hIKrhIstrIguCI4v3J$v%GF$vxFFvlF_ufFHudFAulErvlDTvlCiwcBiwcziw2ydvUw7uUwtsUwmrpxvqXxEpTybpQzKoDBoo1EXnYEyn%YEcnYEdmsEOlZDnlDCnlIBnlbBKlGA5mmA$m^YENpiE$pSCjqrBCq$AVqkAnrkA6skAQsSAmtpBTteCTt9DTt$DgtDEOsPE7sYEHrYEtq" /><g i="21" c="1096" charCode="1096" p="%^Ix1jSA1jSAetREetRE1j$H1j$Het_Let_L1j8P1j8P$vIx$v" /></glyphs></font><font id="40" name="Gilroy Light Charset1_ 5vC0lrobeSD"><glyphs><g i="0" c="1042" charCode="1042" p="#^vHWmxInm7JolKJokLJ5jKJQh7JOgwILftH8frGwe9Fve%ayve%ay$v%JF$v3H_v8ImvdJJuRJEtuKzsvKdruKIpFJAoRIsnvHWm^9FLfxGNfsHKgoIGhqI5joIwksHtlxGpm9Fsm%vzsm%vzLf^JFLu%vzLu%vzIn%JFInbHKn9IKo8JJpaJdr8JJs9IJtbHJuJFLu" /><g i="1" c="1074" charCode="1074" p="#^DFyprG8pQGqodHIndHNmdHnlhGsklFxjvDvj%Wxvj%Wx$v%ZD$vWFZvTG$uQH0uQHysQHtrgHIqJGWpDFyp^vDJkHEKkjFilXFRlYFRmYFVnkFuoIE2pvD2p%az2p%azJk^ZDNu%azNu%azhq%ZDhqdFhqUFTqzGsrAGvszGAtUFaueFMuZDNu" /><g i="2" c="1077" charCode="1077" p="#^yDdjDBfjaA6kJyYkVxqm5xUn4xLp5xFrWx7tMyAueAqvIBgwFDhwwFgwVGvvjIKu5Jst%$HOssHPtkGrudF3vGD4vvB2v3AOtEyysnypq%IJpqIJfqIJ6qJJYpJJOpJJ3oZIAmdI4lQGaksFfjyDdj^yDqkOEqkRF_kUGxlAHBmgIEnqIap%nyapBy3n_zMlnBtkyDqk" /><g i="3" c="1076" charCode="1076" p="%^aINuaIvjpzvjpzLp#ozAr1zLs#HyVt1yNuAwNuAwlzRxlzRx$vFI$vFIlzWJlzWJNu^AzNu#6AQtnADs#FAprFALpFAJkVGJkVGNu" /><g i="4" c="1080" charCode="1080" p="%^9HvjazQtazvjWxvjWx$v1z$vZGGlZG$vfI$vfIvj" /><g i="5" c="1090" charCode="1090" p="%^GGvjkwvjkwJkTAJkTA$v7C$v7CJkGGJk" /><g i="6" c="32" charCode="32" p="#" /><g i="7" c="1089" charCode="1089" p="#^FDhwwFfwZGpvqIzucJ5t%9ItswHFtlGmubF3vFD4v7C3vWAmuKzFt2zssmyfrlyLpmyfo2z2nKzRlWA8l7CrkFDqkaFrklG8lwHQl4I1n%5JqmpIXkYG5kwFejFDdjLBfjgA6kOyYkXxqm5xTn4xLp5xDrXx5tOyyugApvLBfwFDhw" /><g i="8" c="1086" charCode="1086" p="#^FDhwuFfwYGpvrIyuiJ5taKDrcKLpaKTniJqmrIYkYG6kuFfjFDdjOBfjjA6kRyYkZxqm5xTn4xLp5xDrZx5tRyyujApvOBfwFDhw^FD4v8C3vYAmuMzFt3zssmyfrlyLpmyfo3z2nMzRlYA8l8CrkFDqk9FrklG8lxHRldI2nVIfoWILpVIfrdIssxHFtlGmu9F3vFD4v" /><g i="9" c="1048" charCode="1048" p="%^GJ$v$K$v$KveQJvevzytvzveayveay$vkz$vGJYg" /><g i="10" c="1084" charCode="1084" p="%^$JvjvIvjYDGqpzvjWxvjWx$vaz$vazllTDNs2ENsJIplJI$v$J$v" /><g i="11" c="1103" charCode="1103" p="#^AGvj%DBvjvAvjzz_jEysk4yjlwxamvxknxxWoyyWpzzVq4B5r%4x$v%Iy$v%DC7r%kF7r%kF$v%AG$v^DBWppAVpCzdpPyxoNyknPy7mCzrlpAKkDBJk%kFJk%kFWp" /><g i="12" c="1102" charCode="1102" p="#^sIdjIGejiF$jVDMk0D6m8CrnZB9p%az9p%azvj%Wxvj%Wx$v%az$v%azlq%ZBlq8C3s0DptVDKuiFvvIGgwsIhwhKfwLLpveNyu6O5t_ODr$OLp_OTn6OqmeNYkLL6khKfjsIdj^sI4vYG3vLFmuzEFtSDssaDfr9DLpaDfoSD2nzERlLF8lYGrksIqkYJrk8L8lkMRl0N2nINfoJNLpINfr0NsskMFt8LmuYJ3vsI4v" /><g i="13" c="1060" charCode="1060" p="#^hPfnfP5l8ODj2N8i7LmhcJzgJGtg%JGve%nFve%nFtgUCzgZAmh2z8iXxDjRw5lQwfnRwppXxUq2zmsZA9tUCXtnF1u%nF$v%JG$v%JG1ucJXt7L9t2Nms8OUqfPpphPfn^ayfnbyul4zhk_z4jBBridDNhnFIh%nFOsdDJsBB4s_zqr4zdqby0payfn^JGOs%JGIhUINhvKri6M4j$MhkVNulWNfnVN0p$Mdq6MqrvK4sUIJsJGOs" /><g i="14" c="1072" charCode="1072" p="#^WIvj%WIkm7IVkKG4kmFfjyDdjLBfjhA6kQyYkYxqm5xTn4xLp5xDrYx5tQyyuhApvLBfwyDhwmFfwKGqv7IBuWIat%WI$v%cK$v%cKvj^FD4v8C3vYAmuMzFt3zssmyfrlyLpmyfo3z2nMzRlYA8l8CrkFDqk9FrklG8lxHRldI2nVIfoWILpVIfrdIssxHFtlGmu9F3vFD4v" /><g i="15" c="1083" charCode="1083" p="%^4IvjhzvjhzLq#gz8twy3u#Mx_ukwQukw$v#wx6wsyHv#pzgvYz5u#wAWsxALqxAJkQGJkQG$v4I$v" /><g i="16" c="1078" charCode="1078" p="%^$L$v5GvpLLvjcKvjWE9pWEvjFDvjFD9pnyvjQwvjvCvpAw$v7y$vFDRpFD$vWE$vWERpsK$v" /><g i="17" c="1085" charCode="1085" p="%^ZGvjZG9paz9pazvjWxvjWx$vaz$vazlqZGlqZG$vfI$vfIvj" /><g i="18" c="1100" charCode="1100" p="#^TClo%azlo%azvj%Wxvj%Wx$v%TC$v$D$vWExvSF2vqGbu_Gkt$Gas_G0rqG9qSFipWEQo$DmoTClo^TCNu%azNu%azAp%TCAp5EBpUEhqHFZqJFasHFntUE4u5EMuTCNu" /><g i="19" c="83" charCode="83" p="#^xDhwaGfwIHZueJGthJtrfJ_psI3pGH7omGxn2FXmtDsmdC2mfBDliAblLzykczVjczTidzohgAtgjBxf9DvfoEwfhFXfaGmgLG2hkHJhFHxi%NIVhlITgAH2gPGdfIFKeBEee9DdeEBeesAPegznfzyrgSxuhRxWiTxqkEyklpzdmFAMmWBinpDLnLE9oMFEoNG6plHOpWHtqWHvrWH1tPG$tJFZuxD$umBZu2A1uKy4thytr%7x9sLx1uoz8v2BfwxDhw" /><g i="20" c="104" charCode="104" p="#^FDdjcCdj2BSjUzvkazTl%azve%Wxve%Wx$v%az$v%azppbzJnMzCmlAvlkBZkjCqkyDqkkFskgGtldHumdHdo%dH$v%vI$v%vIdotIWlbHBkVFfjFDdj" /><g i="21" c="101" charCode="101" p="#^yDdjDBfjaA6kJyYkVxqm5xUn4xLp5xFrWx7tMyAueAqvIBgwFDhwwFgwVGvvjIKu5Jst%$HOssHPtkGrudF3vGD4vvB2v3AOtEyysnypq%IJpqIJfqIJ6qJJYpJJOpJJ3oZIAmdI4lQGaksFfjyDdj^yDqkOEqkRF_kUGxlAHBmgIEnqIap%nyapBy3n_zMlnBtkyDqk" /><g i="22" c="108" charCode="108" p="%^Wx$vaz$vazLdWxLd" /><g i="23" c="1087" charCode="1087" p="%^fIvjWxvjWx$vaz$vazJkZGJkZG$vfI$v" /><g i="24" c="1079" charCode="1079" p="#^WDypOE7peFnoGFDnGFImGFMlaF_kGEbkKDJjOCejtBdjMzfjFyZjzxHk2xRl%5ysmvytlmzYkeAqktBqkQCskCD5lpEKlqELmpEPnJDqo1D1pOB2p%yA2p%yAhq%hChqzDiqhEWq0Fyr1FAs0FHt9EnuiD2vIB4v4A3v9zqufyMtVxIs%QwkthxBuryqvCzfwIBhweDgwfEMvhFfvNFruiGCtiGFsiGzrHFLq4FXpWDyp" /><g i="25" c="1073" charCode="1073" p="#^nDiw9FhwwGxvTHNuFIutrJassJtqrJLoGIrnWH7mCGoljFEkFDDkNCDkRBVkVAal2ANlbznmyylnQyKlJzKkCAJjqCWiJDmiVESh6GlhYGEgOHWf1ILe%1HaeRGdf6GPfnFogfERg7DihLBWhNzUiMy$jLx5loxwm2xXn4xTp5xQrWxgtLyIu9AvvABhwnDiw^nD2vXB2vQAquJzOt4zIsryBrqy9qyyPohzSn1AUm8BnmgCSlvDRlCFUlTGan8IroaItq8IvsQGMtxF0vnD2v" /><g i="26" c="1095" charCode="1095" p="#^dGvj%dGWplFjqmEwqnDJqnCJqAAKqDzZpHycpGyAn%Gyvj%qxvj%qxAnrxJpKyQq1AWrqCWrsDWrqEJroFwrdG5r%dG$v%vH$v%vHvj" /><g i="27" c="1088" charCode="1088" p="#^yEdjJCfjkB5kYzXkazpm%azvj%Wxvj%Wx$A%az$A%az5tYzzukBpvJCfwyEhwmGfwPHpvhJyu8K5t$KDr1LLp$KTn8KqmhJYkPH6kmGfjyEdj^tE4vZC3vMBmuAAFtTzssbzfrazLpbzfoTz2nAARlMB8lZCrktEqk_FrkaH8lmIRl3J2nMJfoNJLpMJfr3JssmIFtaHmu_F3vtE4v" /><g i="28" c="1099" charCode="1099" p="#^TClo%azlo%azvj%Wxvj%Wx$v%TC$v$D$vWExvSF2vqGbu_Gkt$Gas_G0rqG9qSFipWEQo$DmoTClo^WIvj%WI$v%aK$v%aKvj^TCNu%azNu%azAp%TCAp5EBpUEhqHFZqJFasHFntUE4u5EMuTCNu" /><g i="29" c="1093" charCode="1093" p="%^4I$v5DypNHvjhGvjkCAopyvjTwvjABApAw$v5y$vkCyqyG$v" /><g i="30" c="1075" charCode="1075" p="%^LFvjWxvjWx$vaz$vazJkLFJk" /><g i="31" c="1082" charCode="1082" p="%^vH$vxAvpfHvjvFvjazapazvjWxvjWx$vaz$vazRpOF$v" /><g i="32" c="1094" charCode="1094" p="%^$HNu$HvjJGvjJGNuazNuazvjWxvjWx$vJI$vJIlz$Jlz$JNu" /><g i="33" c="1101" charCode="1101" p="#^kCdjoAejWy5ktxXkJwqm%Qx2npyQlzz8lKArkkCqkNDrkSE3lXFGlAGKmdHOnlH9p%TA9p%TAlq%lHlqdHIrzGMsWFQtQEsuLD3viC4vAA3vpzlufyDtLxqs%Gw4tlxyuOypvgAgwiChweEfwFFpv4HyuSH5tEIDrFILpEITnSHqm5HYkGF6kgEfjkCdj" /><g i="34" c="46" charCode="46" p="#^Gyfw9zewtzWvNzCvOz7vNzEutzku9z0uGy$tay0uSxkuzxEuyx7vzxCvSxWvayewGyfw" /><g i="35" c="40" charCode="40" p="#^fAvy%xBvycATvuz3tNyfqNyfnNyfkuzrhcADexB$b%fA$bXyDedyrhwxfkvxfnwxfqdy3tXyTvfAvy" /><g i="36" c="1081" charCode="1081" p="%^VzkhdGkhdGdgVzdg^9HvjazQtazvjWxvjWx$v1z$vZGGlZG$vfI$vfIvj" /><g i="37" c="115" charCode="115" p="#^NyNmPyElFz2lwArkNBqkQCqkHDUkzEmlZEkm%1GJlvFzkpEVjjDejNBdjRzgjHygkyxflxxNmzx5ojyOo3zupbAQpjBaqrCsqzDKqjEer3FKr5FJs3FVt8EvudD4vTB4vsA3vvzuuyyUtcyTs%7xvtAxJuNyuv$zfwTBhwVDfw6FhvkGiulGJsjGnrzFGqPEZpHDDpzCgprB$okAJozzeoPyLnNyNm" /><g i="38" c="8211" charCode="8211" p="%^ayToGKToGKGnayGn" /><g i="39" c="1091" charCode="1091" p="%^4HvjJCDuGxvjkwvj4CdwOBVw#dBiygA5z#kzVz4yQz4y$A#Iz5B$A1A#iC_y1D9xqIvj" /><g i="40" c="1096" charCode="1096" p="%^dNvjdNNuRGNuRGvjAFvjAFNuazNuazvjWxvjWx$vvO$vvOvj" /><g i="41" c="41" charCode="41" p="#^hyvyBzTviA3t0Bfq1Bfn0BfkiArhBzDehy$b%$w$bkyDe1zrhLzfkLzfnLzfq1z3tkyTv$wvy" /><g i="42" c="49" charCode="49" p="%^$Aveqw4gLwdhOAYfOA$v7C$v7Cve" /><g i="43" c="56" charCode="56" p="#^yFYmHGnmnHml4Ilk5IYi4IphmHmgEGifsFMegEdeTCdeuBdeiAMe6zifoymgGxphFxYiGxlkmyml3znmcAYmNywnXxFo5xNp4xkr5xWsRx1uCy7vVzIvdBgwTChwxEgwQFIv8H7vUH1uFIWsGIkrFINpPHFoZGwnyFYm^ZyYi0zfh5AngbBvfTCvfzEvfEFngKGfhNGYiKGAkEFtlzEmmTCnmbBmm5Atl0zAkZyYi^TC$uPA_uDz1usy4tqykrsyBpDzEoPAHnTCGnXEHn6GEoiHBpkHkriH4t6G1uXE_uTC$u" /><g i="44" c="57" charCode="57" p="#^AIZjzIgiOH_g2HHfKFZeqEeeICde_AeeFzZelyHfBx_gRwgiQwZjRwIlBx$mlyioFz0p_AKpICLpcDLpHDHpaECpDEtp%9A$v%FB$v%vHtn0IMmiIUlAI$kAIZj^ayZjcy_hozMgBAxfICvfPExf0GMgdH_hfHZjdH_l0GdnPEroICtoBAroozdncy_layZj" /><g i="45" c="44" charCode="44" p="%^2AiuvyiuyxvzIyvz" /><g i="46" c="48" charCode="48" p="#^TDhw_FgwrH8vVI0uFJ$rqKZpqKfnqKxkFJwiVIugrHmf_FeeTDdeMBeeiAmfRyug4ywikxxkkxfnkxZp4y$rRy0uiA8vMBgwTDhw^TD$uqBZu3AZsIyYqGyfnIyyj3AyhqBxfTDvfkGxfHHyh3Jyj4Jfn3JYqHHZskGZuTD$u" /><g i="47" c="55" charCode="55" p="%^AwveAwLfOFLf$y$vnA$vaHLfaHve" /><g i="48" c="1098" charCode="1098" p="#^xElo%RAlo%RAvj%$vvj%$vJk%AzJk%Az$v%xE$vGF$vBGxvxH2v5IbuFIktGIasFI0r5I9qxHipBGQoGFmoxElo^xENu%RANu%RAAp%xEApLFBpzGhqnHZqpHasnHntzG4uLFMuxENu" /><g i="49" c="171" charCode="171" p="%^dCYjGAYj$xhoGABsdCBsyzho^JFYjaEYjxBhoaEBsJFBs4Dho" /><g i="50" c="84" charCode="84" p="%^WIveAwveAwLf4CLf4C$vqD$vqDLfWILf" /><g i="51" c="114" charCode="114" p="#^azYl%azvj%Wxvj%Wx$v%az$v%az2pbzsnMzsmmAsliB_kfCwklDxk%lDkj2CijXAUjQzukazYl" /><g i="52" c="97" charCode="97" p="#^WIvj%WIkm7IVkKG4kmFfjyDdjLBfjhA6kQyYkYxqm5xTn4xLp5xDrYx5tQyyuhApvLBfwyDhwmFfwKGqv7IBuWIat%WI$v%cK$v%cKvj^FD4v8C3vYAmuMzFt3zssmyfrlyLpmyfo3z2nMzRlYA8l8CrkFDqk9FrklG8lxHRldI2nVIfoWILpVIfrdIssxHFtlGmu9F3vFD4v" /><g i="53" c="110" charCode="110" p="#^FDdjcCdj2BSjUzvkazTl%azvj%Wxvj%Wx$v%az$v%azppbzJnMzCmlAvlkBZkjCqkyDqkkFskgGtldHumdHdo%dH$v%vI$v%vIdotIWlbHBkVFfjFDdj" /><g i="54" c="112" charCode="112" p="#^yEdjJCfjkB5kYzXkazpm%azvj%Wxvj%Wx$A%az$A%az5tYzzukBpvJCfwyEhwmGfwPHpvhJyu8K5t$KDr1LLp$KTn8KqmhJYkPH6kmGfjyEdj^tE4vZC3vMBmuAAFtTzssbzfrazLpbzfoTz2nAARlMB8lZCrktEqk_FrkaH8lmIRl3J2nMJfoNJLpMJfr3JssmIFtaHmu_F3vtE4v" /><g i="55" c="111" charCode="111" p="#^FDhwuFfwYGpvrIyuiJ5taKDrcKLpaKTniJqmrIYkYG6kuFfjFDdjOBfjjA6kRyYkZxqm5xTn4xLp5xDrZx5tRyyujApvOBfwFDhw^FD4v8C3vYAmuMzFt3zssmyfrlyLpmyfo3z2nMzRlYA8l8CrkFDqk9FrklG8lxHRldI2nVIfoWILpVIfrdIssxHFtlGmu9F3vFD4v" /><g i="56" c="116" charCode="116" p="%^kEJkkEvjBAvjBA$fkzngkzvjAwvjAwJkkzJkkzRs#kzZuBAHv#SBpwkE$vkETu#2D$udCXu#pBTu$Apu#BAXtBARsBAJk" /><g i="57" c="38" charCode="38" p="#^ILxv%iJ$sNJas6KdrrKgqBKdp%qJyoiJAp0JsqLIkrnI1s%VCim4CulyBFk0BQj$ANi1Bjh1Cqg1DxfDEvfZFwfZGdgZHWgnIai%tJxhUIYfAH5fhGeeBEdehDee9CNe2BkfmAmgGznhFzQiFzWj2ALkrAzl2Bfmlz0nsymoAxIpAxlrCxEt7zYuFAfwhDhw0FgwjGHvDH5vvI4u%xKcw^dD$ueB_u5A1uYy3tWykrVy5qDz_olATnZBdn%BH7tMG3uFFxuzE$udD$u" /><g i="58" c="100" charCode="100" p="#^YIve%YIpmaIXkNG5kpFfjADdjMBfjiA6kRyYk_xqm7xTn5xLp7xDr_x5tRyyuiApvMBfwADhwpFfwNGpvaIzuYI5t%YI$v%cK$v%cKve^FD4v8C3vYAmuMzFt3zssmyfrlyLpmyfo3z2nMzRlYA8l8CrkFDqk9FrklG8lyHRleI2nXIfoYILpXIfreIssyHFtlGmu9F3vFD4v" /><g i="59" c="105" charCode="105" p="#^yytgZytgfzbgyzUfyztfyz3ffzOeZyweyyve7yweRxOezx3fyxtfzxUfRxbg7ytgyytg^Wx$v%az$v%azvj%Wxvj" /><g i="60" c="103" charCode="103" p="#^1Jvj%1JpmfIXkSG5kuFfjFDdjRBfjnA6kWyYk3yqmcxTnaxLpcxDr3y5tWyyunApvRBfwFDhwuFfwSGpvfIzu1J5t%1Jpv$IzxIHOypG2A2E4A$B2ASAmzJzGyfzFx%9yhyQyFzkAsARBgB2EhBOFgBbHAABIVzqJByfKhxhKpv%hKvj^JD4vdC3v0BmuQzFt7zssryfrqyLpryfo7z2nQzRl0B8ldCrkJDqkeFrkqG8lCHRljI2n0Jfo1JLp0JfrjIssCHFtqGmueF3vJD4v" /><g i="61" c="187" charCode="187" p="%^yzYj$xYjFAho$xBsyzBscCho^2DYjvBYjaEhovBBs2DBsJFho" /><g i="62" c="1092" charCode="1092" p="#^GLLpFLZnQKym0K7lwIfk1Hmj$Edj%$Eve%LDve%LDdjJBmjdAfkKy7lVxym5xZn4xLp5xxrVxYsKynudAgvJB8wLDhw%LD$A%$E$A%$Ehw1H8wwIgv0KnuQKYsFLxrGLLp^lyLpmyjo0zanGz0mTAjl4CBkLDsk%LD2v4CVuTAcuGzut0zlsmybrlyLp^$E2v%$EskGGBkTHjl4J0mKJanoKjopKLpoKbrKJls4JutTHcuGGVu$E2v" /><g i="63" c="82" charCode="82" p="#^dJ$v%LK$v%pGFo5Iao9JQmdKulfKGjeKeixJ4hRIVfGHdfwGwe4Fve%ayve%ay$v%vz$v%vzQo%1FQo^vzLf%4FLf9GMf0HigUHPgoIIhVIAiWIGjVIMkoIElUHwm0H2n9Gzn4FAn%vzAn" /><g i="64" c="121" charCode="121" p="%^4HvjJCDuGxvjkwvj4CdwOBVw#dBiygA5z#kzVz4yQz4y$A#Iz5B$A1A#iC_y1D9xqIvj" /><g i="65" c="68" charCode="68" p="#^LEve%ayve%ay$v%LE$vbHZv1JPuUKEtXLGr_MHp$Mfn_MPkXLRiUKSg1JIfbHxeLEve^LELu%vzLu%vzLf%LELfQGNfnINgXJMhPKtjHL9lILfnHLlpPK2rXJKsnIKtQGJuLELu" /><g i="66" c="117" charCode="117" p="#^WGvj%WG5qVGNrkGUsMF$tMEyuND4vyC4vNA2vQz1uUy0tTyhr%Tyvj%Bxvj%BxhrDxAtVyWubAfwsChwVDhw2FEvcG$uWGDt%WG$v%aI$v%aIvj" /><g i="67" c="99" charCode="99" p="#^FDhwwFfwZGpvqIzucJ5t%9ItswHFtlGmubF3vFD4v7C3vWAmuKzFt2zssmyfrlyLpmyfo2z2nKzRlWA8l7CrkFDqkaFrklG8lwHQl4I1n%5JqmpIXkYG5kwFejFDdjLBfjgA6kOyYkXxqm5xTn4xLp5xDrXx5tOyyugApvLBfwFDhw" /><g i="68" c="1050" charCode="1050" p="%^2K$vYA$mOJve1IvevzFmvzveayveay$vvz$vvznnhI$v" /><g i="69" c="33" charCode="33" p="#^fyvr%fzvr%vzvj%vzve%$xve%$xvj^LyfwezewyzWvSzCvTz7vSzEuyzkuez0uLy$tgy0uYxkuExEuDx7vExCvYxWvgyewLyfw" /><g i="70" c="63" charCode="63" p="#^vBvr%QCvrSC5qAD2piE$nfF5ncGbmWG9lEH7kGHJiFHfhYGfggGff5FKeXDdexCdeMAdelz2fXxTfkxxh%sy9iUyQgZzag2BvfxCvffEvfgFkgiG8hkGJihGYjzFUkSEPlVDJmZCCnfCLoxBTpvBvr^aCfwFCewZCWvhDCviD7vhDEuZCkuFC0uaC$tGB0umBku3BEu2B7v3BCvmBWvGBewaCfw" /><g i="71" c="1053" charCode="1053" p="%^GJveGJnmvznmvzveayveay$vvz$vvzDnGJDnGJ$v$K$v$Kve" /><g i="72" c="50" charCode="50" p="#^4x$v%4I$v%4IJu%ZyJu%pE9pMFOnIGlmEHTkGHfjFHDhWGwgbGof$EPeQDeetCdeLAdemz2f_xSfaxth%iy9iWyQg_zag2BvftCvfyDvfpEXfhFngOFdhjG2ikGfjiGykuFNlGE0nvDco%4xOu" /><g i="73" c="45" charCode="45" p="%^ayToaHToaHGnayGn" /><g i="74" c="70" charCode="70" p="%^THLfTHveayveay$vvz$vvz$nAH$nAHLmvzLmvzLf" /><g i="75" c="98" charCode="98" p="#^yEdjJCfjkB5kYzXkazpm%azve%Wxve%Wx$v%az$v%az5tYzzukBpvJCfwyEhwmGfwPHpvhJyu8K5t$KDr1LLp$KTn8KqmhJYkPH6kmGfjyEdj^tE4vZC3vMBmuAAFtTzssbzfrazLpbzfoTz2nAARlMB8lZCrktEqk_FrkaH8lmIRl3J2nMJfoNJLpMJfr3JssmIFtaHmu_F3vtE4v" /><g i="76" c="71" charCode="71" p="#^QORn%2GRn%2G5p%tN5pkNLqsM5sALqt1KcuvI_unG$u0EZufCYtuAWsvzarwyqpvyfnwy4luzkjtAAhcCzgYDxfhGvfnIwf2KvgKLuhDM9j%ONsiHMxgJKofLIfehGdeBDfeyBsfvzFglyHicxJkaxfnbxNplyPrwzRtAB2vEDfwnGhw$IfwUKcvNM9uONpsPOFqQOxo" /><g i="77" c="51" charCode="51" p="#^hDNl%tHLf%tHve%pxve%pxLf%YFLf%xB1m%5CVm%tCVmtEWmIF_nXG2pZGYqZGdsoG7tPF1uPEwuPD$uxC$uSA$uIzjuyyCt2yis%YwYsDxzu5zqvAAgwxChw5EgwoFEvIG0vuHQthIEsiIYqhIppCHjoXGcnOFzmGEWlhDNl" /><g i="78" c="53" charCode="53" p="#^FCDl%lzDl%LzLf%QHLf%QHve%Ayve%ZxVm%FCVmEEWmTF_n6H2p9HYq6HSsTFWtEE_uFC$u0B$uSzguIywtfy5s%7xLsMxuufznvKAgwFChwfEgwzFEvTG0vFHQtsIEstIYqsIfpFH3oTGTmzFfmfEDlFCDl" /><g i="79" c="59" charCode="59" p="#^5zLlAzKlUzqldA6ldADkdA8kUzQjAzwj5zvjCywjiyQj_x8kZxDk_x6liyqlCyKl5zLl^2Aiu%vyiu%yxvz%Iyvz" /><g i="80" c="1056" charCode="1056" p="#^7Eve%ayve%ay$v%vz$v%vzkp%7EkpJFjpXGCo9IVnSIImzJulAJWjzJmiSI8h9IWfXGdfJFwe7Eve^7E4o%vz4o%vzLf%7ELfYFNf4HXgdI4ifIWjdIMl4HVmYF2o7E4o" /><g i="81" c="1069" charCode="1069" p="#^vEde3Cfe5Anf7yug$wqi%ay5j5zthLAvgqCwfvEvfIGwfnIsg2Koh1L$i1MCkaMDm%iCDm%iCTn%aMTn1MUp1Lvr2K6tnI2uIG_uvE$uoCZuJA_t2z$s9ykr%Yw$r2yYt1A6v1CfwvEhwbHfwcJ2veLRtmMPrvNNpxNfnvNJkmMHieLFgcJsfbHfevEde" /><g i="82" c="1055" charCode="1055" p="%^GKveayveay$vvz$vvzLfkJLfkJ$vGK$v" /><g i="83" c="1044" charCode="1044" p="%^sKLusKveFzveFzto#Dz$q6zus#CyYtRxLuswLuswlzOxlzOx$vYK$vYKlziMlziMLu^ZAvoZALf7JLf7JLuqzLu#4ATtwAns#YATqZAvo" /><g i="84" c="1097" charCode="1097" p="%^vONuvOvjdNvjdNNuRGNuRGvjAFvjAFNuazNuazvjWxvjWx$vZO$vZOlzfQlzfQNu" /><g i="85" c="1057" charCode="1057" p="#^hGhwMIfwKK6vJMYtQN$r%FMkrLL$s3K_toIZuhG$uYDZucCYttAWsuzarwyqpvyfnwy4luzkjtAAhcCzgYDxfhGvfnIwf1KvgILthBM5j%NNqiFMugHKnfJIfehGdeBDfeyBsfvzFglyHicxJkaxfncxNplyPrvzRtyB2vBDfwhGhw" /><g i="86" c="69" charCode="69" p="%^vzLuvzOnvHOnvHymvzymvzLf7ILf7Iveayveay$vfI$vfILu" /><g i="87" c="120" charCode="120" p="%^4I$v5DypNHvjhGvjkCAopyvjTwvjABApAw$v5y$vkCyqyG$v" /><g i="88" c="77" charCode="77" p="%^$NvekMve4GRoQzveayveay$vvz$vvzsgZFcrcGcrGMsgGM$v$N$v" /><g i="89" c="66" charCode="66" p="#^vHWmxInm7JolKJokLJ5jKJQh7JOgwILftH8frGwe9Fve%ayve%ay$v%JF$v3H_v8ImvdJJuRJEtuKzsvKdruKIpFJAoRIsnvHWm^9FLfxGNfsHKgoIGhqI5joIwksHtlxGpm9Fsm%vzsm%vzLf^JFLu%vzLu%vzIn%JFInbHKn9IKo8JJpaJdr8JJs9IJtbHJuJFLu" /><g i="90" c="80" charCode="80" p="#^7Eve%ayve%ay$v%vz$v%vzkp%7EkpJFjpXGCo9IVnSIImzJulAJWjzJmiSI8h9IWfXGdfJFwe7Eve^7E4o%vz4o%vzLf%7ELfYFNf4HXgdI4ifIWjdIMl4HVmYF2o7E4o" /><g i="91" c="109" charCode="109" p="#^hLdj$JdjUIRjOHtk5HNlBGxkAFUjAEejcDdj_BdjXAOjUzmkazFl%azvj%Wxvj%Wx$v%az$v%az1pbzqnJzpmgAol8BVk0Cqk2DqkwErknFmleGhmfG4o%fG$v%vH$v%vH1pxHEmAIxlEJpkfLqkKMrkENmlyOhmAO4o%AO$v%QP$v%QP4oOPJlyOukiNejhLdj" /><g i="92" c="67" charCode="67" p="#^hGhwMIfwKK6vJMYtQN$r%FMkrLL$s3K_toIZuhG$uYDZucCYttAWsuzarwyqpvyfnwy4luzkjtAAhcCzgYDxfhGvfnIwf1KvgILthBM5j%NNqiFMugHKnfJIfehGdeBDfeyBsfvzFglyHicxJkaxfncxNplyPrvzRtyB2vBDfwhGhw" /><g i="93" c="118" charCode="118" p="%^5HvjnCIuGxvjkwvjDB$v9D$vqIvj" /><g i="94" c="75" charCode="75" p="%^2K$vYA$mOJve1IvevzFmvzveayveay$vvz$vvznnhI$v" /><g i="95" c="76" charCode="76" p="%^vzLuvzveayveay$vLH$vLHLu" /><g i="96" c="58" charCode="58" p="#^GyLl9zKltzqlNz6lOzDkNz8ktzQj9zwjGyvjaywjSxQjzx8kyxDkzx6lSxqlayKlGyLl^Gyfw9zewtzWvNzCvOz7vNzEutzku9z0uGy$tay0uSxkuzxEuyx7vzxCvSxWvayewGyfw" /><g i="97" c="107" charCode="107" p="%^vH$vxAvpfHvjvFvjazapazveWxveWx$vaz$vazRpOF$v" /><g i="98" c="65" charCode="65" p="%^YJ$vlL$vAEveaDvenw$vNx$vtzyrfIyr^ZziqTD7gNHiq" /></glyphs></font><font id="50" name="Gilroy LightBold Charset1_ 5ia7P3733NU"><glyphs><g i="0" c="1056" charCode="1056" p="#^7Eve%ayve%ay$v%vz$v%vzkp%7EkpJFjpXGCo9IVnSIImzJulAJWjzJmiSI8h9IWfXGdfJFwe7Eve^7E4o%vz4o%vzLf%7ELfYFNf4HXgdI4ifIWjdIMl4HVmYF2o7E4o" /><g i="1" c="1086" charCode="1086" p="#^FDhwuFfwYGpvrIyuiJ5taKDrcKLpaKTniJqmrIYkYG6kuFfjFDdjOBfjjA6kRyYkZxqm5xTn4xLp5xDrZx5tRyyujApvOBfwFDhw^FD4v8C3vYAmuMzFt3zssmyfrlyLpmyfo3z2nMzRlYA8l8CrkFDqk9FrklG8lxHRldI2nVIfoWILpVIfrdIssxHFtlGmu9F3vFD4v" /><g i="2" c="1078" charCode="1078" p="%^$L$v5GvpLLvjcKvjWE9pWEvjFDvjFD9pnyvjQwvjvCvpAw$v7y$vFDRpFD$vWE$vWERpsK$v" /><g i="3" c="1076" charCode="1076" p="%^aINuaIvjpzvjpzLp#ozAr1zLs#HyVt1yNuAwNuAwlzRxlzRx$vFI$vFIlzWJlzWJNu^AzNu#6AQtnADs#FAprFALpFAJkVGJkVGNu" /><g i="4" c="1077" charCode="1077" p="#^yDdjDBfjaA6kJyYkVxqm5xUn4xLp5xFrWx7tMyAueAqvIBgwFDhwwFgwVGvvjIKu5Jst%$HOssHPtkGrudF3vGD4vvB2v3AOtEyysnypq%IJpqIJfqIJ6qJJYpJJOpJJ3oZIAmdI4lQGaksFfjyDdj^yDqkOEqkRF_kUGxlAHBmgIEnqIap%nyapBy3n_zMlnBtkyDqk" /><g i="5" c="1085" charCode="1085" p="%^ZGvjZG9paz9pazvjWxvjWx$vaz$vazlqZGlqZG$vfI$vfIvj" /><g i="6" c="1080" charCode="1080" p="%^9HvjazQtazvjWxvjWx$v1z$vZGGlZG$vfI$vfIvj" /><g i="7" c="32" charCode="32" p="#" /><g i="8" c="83" charCode="83" p="#^xDhwaGfwIHZueJGthJtrfJ_psI3pGH7omGxn2FXmtDsmdC2mfBDliAblLzykczVjczTidzohgAtgjBxf9DvfoEwfhFXfaGmgLG2hkHJhFHxi%NIVhlITgAH2gPGdfIFKeBEee9DdeEBeesAPegznfzyrgSxuhRxWiTxqkEyklpzdmFAMmWBinpDLnLE9oMFEoNG6plHOpWHtqWHvrWH1tPG$tJFZuxD$umBZu2A1uKy4thytr%7x9sLx1uoz8v2BfwxDhw" /><g i="9" c="104" charCode="104" p="#^FDdjcCdj2BSjUzvkazTl%azve%Wxve%Wx$v%az$v%azppbzJnMzCmlAvlkBZkjCqkyDqkkFskgGtldHumdHdo%dH$v%vI$v%vIdotIWlbHBkVFfjFDdj" /><g i="10" c="101" charCode="101" p="#^yDdjDBfjaA6kJyYkVxqm5xUn4xLp5xFrWx7tMyAueAqvIBgwFDhwwFgwVGvvjIKu5Jst%$HOssHPtkGrudF3vGD4vvB2v3AOtEyysnypq%IJpqIJfqIJ6qJJYpJJOpJJ3oZIAmdI4lQGaksFfjyDdj^yDqkOEqkRF_kUGxlAHBmgIEnqIap%nyapBy3n_zMlnBtkyDqk" /><g i="11" c="108" charCode="108" p="%^Wx$vaz$vazLdWxLd" /><g i="12" c="1052" charCode="1052" p="%^$NvekMve4GRoQzveayveay$vvz$vvzsgZFcrcGcrGMsgGM$v$N$v" /><g i="13" c="1072" charCode="1072" p="#^WIvj%WIkm7IVkKG4kmFfjyDdjLBfjhA6kQyYkYxqm5xTn4xLp5xDrYx5tQyyuhApvLBfwyDhwmFfwKGqv7IBuWIat%WI$v%cK$v%cKvj^FD4v8C3vYAmuMzFt3zssmyfrlyLpmyfo3z2nMzRlYA8l8CrkFDqk9FrklG8lxHRldI2nVIfoWILpVIfrdIssxHFtlGmu9F3vFD4v" /><g i="14" c="1088" charCode="1088" p="#^yEdjJCfjkB5kYzXkazpm%azvj%Wxvj%Wx$A%az$A%az5tYzzukBpvJCfwyEhwmGfwPHpvhJyu8K5t$KDr1LLp$KTn8KqmhJYkPH6kmGfjyEdj^tE4vZC3vMBmuAAFtTzssbzfrazLpbzfoTz2nAARlMB8lZCrktEqk_FrkaH8lmIRl3J2nMJfoNJLpMJfr3JssmIFtaHmu_F3vtE4v" /><g i="15" c="1082" charCode="1082" p="%^vH$vxAvpfHvjvFvjazapazvjWxvjWx$vaz$vazRpOF$v" /><g i="16" c="1091" charCode="1091" p="%^4HvjJCDuGxvjkwvj4CdwOBVw#dBiygA5z#kzVz4yQz4y$A#Iz5B$A1A#iC_y1D9xqIvj" /><g i="17" c="1089" charCode="1089" p="#^FDhwwFfwZGpvqIzucJ5t%9ItswHFtlGmubF3vFD4v7C3vWAmuKzFt2zssmyfrlyLpmyfo2z2nKzRlWA8l7CrkFDqkaFrklG8lwHQl4I1n%5JqmpIXkYG5kwFejFDdjLBfjgA6kOyYkXxqm5xTn4xLp5xDrXx5tOyyugApvLBfwFDhw" /><g i="18" c="1057" charCode="1057" p="#^hGhwMIfwKK6vJMYtQN$r%FMkrLL$s3K_toIZuhG$uYDZucCYttAWsuzarwyqpvyfnwy4luzkjtAAhcCzgYDxfhGvfnIwf1KvgILthBM5j%NNqiFMugHKnfJIfehGdeBDfeyBsfvzFglyHicxJkaxfncxNplyPrvzRtyB2vBDfwhGhw" /><g i="19" c="1101" charCode="1101" p="#^kCdjoAejWy5ktxXkJwqm%Qx2npyQlzz8lKArkkCqkNDrkSE3lXFGlAGKmdHOnlH9p%TA9p%TAlq%lHlqdHIrzGMsWFQtQEsuLD3viC4vAA3vpzlufyDtLxqs%Gw4tlxyuOypvgAgwiChweEfwFFpv4HyuSH5tEIDrFILpEITnSHqm5HYkGF6kgEfjkCdj" /><g i="20" c="1084" charCode="1084" p="%^$JvjvIvjYDGqpzvjWxvjWx$vaz$vazllTDNs2ENsJIplJI$v$J$v" /><g i="21" c="1102" charCode="1102" p="#^sIdjIGejiF$jVDMk0D6m8CrnZB9p%az9p%azvj%Wxvj%Wx$v%az$v%azlq%ZBlq8C3s0DptVDKuiFvvIGgwsIhwhKfwLLpveNyu6O5t_ODr$OLp_OTn6OqmeNYkLL6khKfjsIdj^sI4vYG3vLFmuzEFtSDssaDfr9DLpaDfoSD2nzERlLF8lYGrksIqkYJrk8L8lkMRl0N2nINfoJNLpINfr0NsskMFt8LmuYJ3vsI4v" /><g i="22" c="1083" charCode="1083" p="%^4IvjhzvjhzLq#gz8twy3u#Mx_ukwQukw$v#wx6wsyHv#pzgvYz5u#wAWsxALqxAJkQGJkQG$v4I$v" /><g i="23" c="1103" charCode="1103" p="#^AGvj%DBvjvAvjzz_jEysk4yjlwxamvxknxxWoyyWpzzVq4B5r%4x$v%Iy$v%DC7r%kF7r%kF$v%AG$v^DBWppAVpCzdpPyxoNyknPy7mCzrlpAKkDBJk%kFJk%kFWp" /><g i="24" c="46" charCode="46" p="#^Gyfw9zewtzWvNzCvOz7vNzEutzku9z0uGy$tay0uSxkuzxEuyx7vzxCvSxWvayewGyfw" /><g i="25" c="1044" charCode="1044" p="%^sKLusKveFzveFzto#Dz$q6zus#CyYtRxLuswLuswlzOxlzOx$vYK$vYKlziMlziMLu^ZAvoZALf7JLf7JLuqzLu#4ATtwAns#YATqZAvo" /><g i="26" c="1053" charCode="1053" p="%^GJveGJnmvznmvzveayveay$vvz$vvzDnGJDnGJ$v$K$v$Kve" /><g i="27" c="1090" charCode="1090" p="%^GGvjkwvjkwJkTAJkTA$v7C$v7CJkGGJk" /><g i="28" c="8470" charCode="8470" p="#^FQylkSwllTuknUsjpUVhoUTgVT2gqTdfASKeKReeFQdezPeeJOKeTNdfoN2gVMTgVMVhXMsjZNuk$OwlFQyl^GJve%GJyt%kzve%ayve%ay$v%vz$v%vzYg%QJ$v%$K$v%$Kve^FQpkyPnkSOGjaOZi9OVhaOPgSO6gyPpfFQnfMRpfrS6g7TPg9TVh7TZisSGjNRnkFQpk^cNLo%7ULo%7Uxn%cNxn" /><g i="29" c="49" charCode="49" p="%^$Aveqw4gLwdhOAYfOA$v7C$v7Cve" /><g i="30" c="1074" charCode="1074" p="#^DFyprG8pQGqodHIndHNmdHnlhGsklFxjvDvj%Wxvj%Wx$v%ZD$vWFZvTG$uQH0uQHysQHtrgHIqJGWpDFyp^vDJkHEKkjFilXFRlYFRmYFVnkFuoIE2pvD2p%az2p%azJk^ZDNu%azNu%azhq%ZDhqdFhqUFTqzGsrAGvszGAtUFaueFMuZDNu" /><g i="31" c="1060" charCode="1060" p="#^hPfnfP5l8ODj2N8i7LmhcJzgJGtg%JGve%nFve%nFtgUCzgZAmh2z8iXxDjRw5lQwfnRwppXxUq2zmsZA9tUCXtnF1u%nF$v%JG$v%JG1ucJXt7L9t2Nms8OUqfPpphPfn^ayfnbyul4zhk_z4jBBridDNhnFIh%nFOsdDJsBB4s_zqr4zdqby0payfn^JGOs%JGIhUINhvKri6M4j$MhkVNulWNfnVN0p$Mdq6MqrvK4sUIJsJGOs" /><g i="32" c="50" charCode="50" p="#^4x$v%4I$v%4IJu%ZyJu%pE9pMFOnIGlmEHTkGHfjFHDhWGwgbGof$EPeQDeetCdeLAdemz2f_xSfaxth%iy9iWyQg_zag2BvftCvfyDvfpEXfhFngOFdhjG2ikGfjiGykuFNlGE0nvDco%4xOu" /><g i="33" c="1073" charCode="1073" p="#^nDiw9FhwwGxvTHNuFIutrJassJtqrJLoGIrnWH7mCGoljFEkFDDkNCDkRBVkVAal2ANlbznmyylnQyKlJzKkCAJjqCWiJDmiVESh6GlhYGEgOHWf1ILe%1HaeRGdf6GPfnFogfERg7DihLBWhNzUiMy$jLx5loxwm2xXn4xTp5xQrWxgtLyIu9AvvABhwnDiw^nD2vXB2vQAquJzOt4zIsryBrqy9qyyPohzSn1AUm8BnmgCSlvDRlCFUlTGan8IroaItq8IvsQGMtxF0vnD2v" /><g i="34" c="1099" charCode="1099" p="#^TClo%azlo%azvj%Wxvj%Wx$v%TC$v$D$vWExvSF2vqGbu_Gkt$Gas_G0rqG9qSFipWEQo$DmoTClo^WIvj%WI$v%aK$v%aKvj^TCNu%azNu%azAp%TCAp5EBpUEhqHFZqJFasHFntUE4u5EMuTCNu" /><g i="35" c="1095" charCode="1095" p="#^dGvj%dGWplFjqmEwqnDJqnCJqAAKqDzZpHycpGyAn%Gyvj%qxvj%qxAnrxJpKyQq1AWrqCWrsDWrqEJroFwrdG5r%dG$v%vH$v%vHvj" /><g i="36" c="1081" charCode="1081" p="%^VzkhdGkhdGdgVzdg^9HvjazQtazvjWxvjWx$v1z$vZGGlZG$vfI$vfIvj" /><g i="37" c="1100" charCode="1100" p="#^TClo%azlo%azvj%Wxvj%Wx$v%TC$v$D$vWExvSF2vqGbu_Gkt$Gas_G0rqG9qSFipWEQo$DmoTClo^TCNu%azNu%azAp%TCAp5EBpUEhqHFZqJFasHFntUE4u5EMuTCNu" /><g i="38" c="1092" charCode="1092" p="#^GLLpFLZnQKym0K7lwIfk1Hmj$Edj%$Eve%LDve%LDdjJBmjdAfkKy7lVxym5xZn4xLp5xxrVxYsKynudAgvJB8wLDhw%LD$A%$E$A%$Ehw1H8wwIgv0KnuQKYsFLxrGLLp^lyLpmyjo0zanGz0mTAjl4CBkLDsk%LD2v4CVuTAcuGzut0zlsmybrlyLp^$E2v%$EskGGBkTHjl4J0mKJanoKjopKLpoKbrKJls4JutTHcuGGVu$E2v" /><g i="39" c="1087" charCode="1087" p="%^fIvjWxvjWx$vaz$vazJkZGJkZG$vfI$v" /><g i="40" c="1075" charCode="1075" p="%^LFvjWxvjWx$vaz$vazJkLFJk" /><g i="41" c="1079" charCode="1079" p="#^WDypOE7peFnoGFDnGFImGFMlaF_kGEbkKDJjOCejtBdjMzfjFyZjzxHk2xRl%5ysmvytlmzYkeAqktBqkQCskCD5lpEKlqELmpEPnJDqo1D1pOB2p%yA2p%yAhq%hChqzDiqhEWq0Fyr1FAs0FHt9EnuiD2vIB4v4A3v9zqufyMtVxIs%QwkthxBuryqvCzfwIBhweDgwfEMvhFfvNFruiGCtiGFsiGzrHFLq4FXpWDyp" /><g i="42" c="51" charCode="51" p="#^hDNl%tHLf%tHve%pxve%pxLf%YFLf%xB1m%5CVm%tCVmtEWmIF_nXG2pZGYqZGdsoG7tPF1uPEwuPD$uxC$uSA$uIzjuyyCt2yis%YwYsDxzu5zqvAAgwxChw5EgwoFEvIG0vuHQthIEsiIYqhIppCHjoXGcnOFzmGEWlhDNl" /><g i="43" c="55" charCode="55" p="%^AwveAwLfOFLf$y$vnA$vaHLfaHve" /><g i="44" c="52" charCode="52" p="%^IJ4rsH4rsHAl7GAl7G4ray4rOEvelDveIw4rIwks7Gks7G$vsH$vsHksIJks" /><g i="45" c="53" charCode="53" p="#^FCDl%lzDl%LzLf%QHLf%QHve%Ayve%ZxVm%FCVmEEWmTF_n6H2p9HYq6HSsTFWtEE_uFC$u0B$uSzguIywtfy5s%7xLsMxuufznvKAgwFChwfEgwzFEvTG0vFHQtsIEstIYqsIfpFH3oTGTmzFfmfEDlFCDl" /><g i="46" c="72" charCode="72" p="%^GJveGJnmvznmvzveayveay$vvz$vvzDnGJDnGJ$v$K$v$Kve" /><g i="47" c="69" charCode="69" p="%^vzLuvzOnvHOnvHymvzymvzLf7ILf7Iveayveay$vfI$vfILu" /><g i="48" c="76" charCode="76" p="%^vzLuvzveayveay$vLH$vLHLu" /><g i="49" c="73" charCode="73" p="%^ayveay$vvz$vvzve" /><g i="50" c="88" charCode="88" p="%^LJ$vWD$mqJveVHveaDQlqyveVwvepC$mAw$v7y$vaDcodI$v" /><g i="51" c="85" charCode="85" p="#^kEhwgGgwIHwv8JLuXJotKK0sLK9q%LKve%qJve%qJ9qqJks7IFtQGZukE$uRBZuyAFtgzksfz9q%fzve%Wxve%Wx9qXx0sJyotwzLuYAwvoCgwkEhw" /><g i="52" c="84" charCode="84" p="%^WIveAwveAwLf4CLf4C$vqD$vqDLfWILf" /><g i="53" c="82" charCode="82" p="#^dJ$v%LK$v%pGFo5Iao9JQmdKulfKGjeKeixJ4hRIVfGHdfwGwe4Fve%ayve%ay$v%vz$v%vzQo%1FQo^vzLf%4FLf9GMf0HigUHPgoIIhVIAiWIGjVIMkoIElUHwm0H2n9Gzn4FAn%vzAn" /><g i="54" c="65" charCode="65" p="%^YJ$vlL$vAEveaDvenw$vNx$vtzyrfIyr^ZziqTD7gNHiq" /><g i="55" c="1045" charCode="1045" p="%^vzLuvzOnvHOnvHymvzymvzLf7ILf7Iveayveay$vfI$vfILu" /><g i="56" c="44" charCode="44" p="%^2AiuvyiuyxvzIyvz" /><g i="57" c="70" charCode="70" p="%^THLfTHveayveay$vvz$vvz$nAH$nAHLmvzLmvzLf" /><g i="58" c="114" charCode="114" p="#^azYl%azvj%Wxvj%Wx$v%az$v%az2pbzsnMzsmmAsliB_kfCwklDxk%lDkj2CijXAUjQzukazYl" /><g i="59" c="97" charCode="97" p="#^WIvj%WIkm7IVkKG4kmFfjyDdjLBfjhA6kQyYkYxqm5xTn4xLp5xDrYx5tQyyuhApvLBfwyDhwmFfwKGqv7IBuWIat%WI$v%cK$v%cKvj^FD4v8C3vYAmuMzFt3zssmyfrlyLpmyfo3z2nMzRlYA8l8CrkFDqk9FrklG8lxHRldI2nVIfoWILpVIfrdIssxHFtlGmu9F3vFD4v" /><g i="60" c="105" charCode="105" p="#^yytgZytgfzbgyzUfyztfyz3ffzOeZyweyyve7yweRxOezx3fyxtfzxUfRxbg7ytgyytg^Wx$v%az$v%azvj%Wxvj" /><g i="61" c="1093" charCode="1093" p="%^4I$v5DypNHvjhGvjkCAopyvjTwvjABApAw$v5y$vkCyqyG$v" /><g i="62" c="45" charCode="45" p="%^ayToaHToaHGnayGn" /><g i="63" c="1054" charCode="1054" p="#^cGhwLIfwNK2vPMRt$NPrcPNpdPfncPJk$NHiPMFgNKsfLIfecGdeEDfeCBsfAzFgoyHicxJkaxfncxNpoyPrAzRtCB2vEDfwcGhw^cG$u0EZuhCYtyAWsxzarwyqpvyfnwy4lxzkjyAAhhCzg0ExfcGvfoIxf7KzgSLAhSMkjTN4lVNfnTNqpSMarSLWs7KYtoIZucG$u" /><g i="64" c="1098" charCode="1098" p="#^xElo%RAlo%RAvj%$vvj%$vJk%AzJk%Az$v%xE$vGF$vBGxvxH2v5IbuFIktGIasFI0r5I9qxHipBGQoGFmoxElo^xENu%RANu%RAAp%xEApLFBpzGhqnHZqpHasnHntzG4uLFMuxENu" /><g i="65" c="37" charCode="37" p="#^pBGl6DEl9EBkcFyjdFYhbFmg7Ejf4DgepBdeJzgeFyjfCxmgAxYhCxyjFyBkJzElpBGl^pBxkfAvkyzNjRy3jQyYhRyRgyz7gfApfpBnfzCpfgD7g_DRg$DYh_D3jgDNjzCvkpBxk^xyLt%lzdu%fLTg%pKpg^tIhw9KewcLbvgM8uiMysgMYqcLVp9KSotIQoOGSoKFVpHEYqFEysHE8uKFbvOGewtIhw^tI7vkH5vDGnuWFFtVFysWFrrDGJqkH$ptIZpEJ$plKJq3Lrr4Lys3LFtlKnuEJ5vtI7v" /><g i="66" c="1042" charCode="1042" p="#^vHWmxInm7JolKJokLJ5jKJQh7JOgwILftH8frGwe9Fve%ayve%ay$v%JF$v3H_v8ImvdJJuRJEtuKzsvKdruKIpFJAoRIsnvHWm^9FLfxGNfsHKgoIGhqI5joIwksHtlxGpm9Fsm%vzsm%vzLf^JFLu%vzLu%vzIn%JFInbHKn9IKo8JJpaJdr8JJs9IJtbHJuJFLu" /></glyphs></font></bwFonts>